{"fireeye.speakeasy/run_speakeasy.py": {"loc": 240, "lloc": 161, "sloc": 192, "comments": 7, "multi": 9, "blank": 32, "single_comments": 7}, "fireeye.speakeasy/setup.py": {"loc": 38, "lloc": 10, "sloc": 33, "comments": 1, "multi": 0, "blank": 4, "single_comments": 1}, "fireeye.speakeasy/examples/dbgview.py": {"loc": 58, "lloc": 27, "sloc": 33, "comments": 3, "multi": 3, "blank": 19, "single_comments": 3}, "fireeye.speakeasy/examples/emu_dll.py": {"loc": 110, "lloc": 50, "sloc": 51, "comments": 15, "multi": 19, "blank": 25, "single_comments": 15}, "fireeye.speakeasy/examples/emu_exe.py": {"loc": 69, "lloc": 30, "sloc": 32, "comments": 7, "multi": 11, "blank": 19, "single_comments": 7}, "fireeye.speakeasy/examples/upx_unpack.py": {"loc": 67, "lloc": 39, "sloc": 40, "comments": 7, "multi": 3, "blank": 17, "single_comments": 7}, "fireeye.speakeasy/examples/usb_emu.py": {"loc": 259, "lloc": 156, "sloc": 177, "comments": 10, "multi": 3, "blank": 70, "single_comments": 9}, "fireeye.speakeasy/speakeasy/binemu.py": {"loc": 1076, "lloc": 749, "sloc": 707, "comments": 15, "multi": 206, "blank": 148, "single_comments": 15}, "fireeye.speakeasy/speakeasy/common.py": {"loc": 257, "lloc": 168, "sloc": 165, "comments": 4, "multi": 46, "blank": 42, "single_comments": 4}, "fireeye.speakeasy/speakeasy/errors.py": {"loc": 81, "lloc": 35, "sloc": 24, "comments": 1, "multi": 33, "blank": 23, "single_comments": 1}, "fireeye.speakeasy/speakeasy/memmgr.py": {"loc": 367, "lloc": 225, "sloc": 200, "comments": 7, "multi": 91, "blank": 69, "single_comments": 7}, "fireeye.speakeasy/speakeasy/profiler.py": {"loc": 503, "lloc": 408, "sloc": 331, "comments": 4, "multi": 74, "blank": 95, "single_comments": 3}, "fireeye.speakeasy/speakeasy/speakeasy.py": {"loc": 895, "lloc": 394, "sloc": 344, "comments": 6, "multi": 390, "blank": 154, "single_comments": 7}, "fireeye.speakeasy/speakeasy/struct.py": {"loc": 335, "lloc": 222, "sloc": 202, "comments": 18, "multi": 58, "blank": 58, "single_comments": 17}, "fireeye.speakeasy/speakeasy/version.py": {"loc": 1, "lloc": 1, "sloc": 1, "comments": 0, "multi": 0, "blank": 0, "single_comments": 0}, "fireeye.speakeasy/speakeasy/__init__.py": {"loc": 12, "lloc": 6, "sloc": 6, "comments": 3, "multi": 0, "blank": 3, "single_comments": 3}, "fireeye.speakeasy/speakeasy/engines/unicorn_eng.py": {"loc": 279, "lloc": 148, "sloc": 199, "comments": 12, "multi": 15, "blank": 44, "single_comments": 21}, "fireeye.speakeasy/speakeasy/engines/__init__.py": {"loc": 3, "lloc": 1, "sloc": 1, "comments": 1, "multi": 0, "blank": 1, "single_comments": 1}, "fireeye.speakeasy/speakeasy/windows/com.py": {"loc": 69, "lloc": 44, "sloc": 47, "comments": 5, "multi": 6, "blank": 11, "single_comments": 5}, "fireeye.speakeasy/speakeasy/windows/common.py": {"loc": 607, "lloc": 403, "sloc": 410, "comments": 20, "multi": 59, "blank": 121, "single_comments": 17}, "fireeye.speakeasy/speakeasy/windows/cryptman.py": {"loc": 66, "lloc": 47, "sloc": 44, "comments": 1, "multi": 6, "blank": 15, "single_comments": 1}, "fireeye.speakeasy/speakeasy/windows/driveman.py": {"loc": 48, "lloc": 30, "sloc": 30, "comments": 1, "multi": 3, "blank": 14, "single_comments": 1}, "fireeye.speakeasy/speakeasy/windows/fileman.py": {"loc": 377, "lloc": 298, "sloc": 283, "comments": 6, "multi": 23, "blank": 65, "single_comments": 6}, "fireeye.speakeasy/speakeasy/windows/hammer.py": {"loc": 123, "lloc": 68, "sloc": 73, "comments": 26, "multi": 11, "blank": 15, "single_comments": 24}, "fireeye.speakeasy/speakeasy/windows/ioman.py": {"loc": 31, "lloc": 18, "sloc": 17, "comments": 3, "multi": 4, "blank": 7, "single_comments": 3}, "fireeye.speakeasy/speakeasy/windows/kernel.py": {"loc": 727, "lloc": 477, "sloc": 475, "comments": 39, "multi": 66, "blank": 148, "single_comments": 38}, "fireeye.speakeasy/speakeasy/windows/netman.py": {"loc": 402, "lloc": 288, "sloc": 282, "comments": 4, "multi": 22, "blank": 94, "single_comments": 4}, "fireeye.speakeasy/speakeasy/windows/objman.py": {"loc": 955, "lloc": 655, "sloc": 653, "comments": 13, "multi": 79, "blank": 211, "single_comments": 12}, "fireeye.speakeasy/speakeasy/windows/regman.py": {"loc": 216, "lloc": 162, "sloc": 148, "comments": 10, "multi": 21, "blank": 38, "single_comments": 9}, "fireeye.speakeasy/speakeasy/windows/sessman.py": {"loc": 164, "lloc": 117, "sloc": 103, "comments": 6, "multi": 22, "blank": 33, "single_comments": 6}, "fireeye.speakeasy/speakeasy/windows/win32.py": {"loc": 634, "lloc": 425, "sloc": 408, "comments": 28, "multi": 72, "blank": 126, "single_comments": 28}, "fireeye.speakeasy/speakeasy/windows/winemu.py": {"loc": 2103, "lloc": 1461, "sloc": 1401, "comments": 58, "multi": 294, "blank": 352, "single_comments": 56}, "fireeye.speakeasy/speakeasy/windows/__init__.py": {"loc": 0, "lloc": 0, "sloc": 0, "comments": 0, "multi": 0, "blank": 0, "single_comments": 0}, "fireeye.speakeasy/speakeasy/windows/kernel_mods/kernel_mod.py": {"loc": 12, "lloc": 7, "sloc": 7, "comments": 1, "multi": 0, "blank": 4, "single_comments": 1}, "fireeye.speakeasy/speakeasy/windows/kernel_mods/volmgr.py": {"loc": 39, "lloc": 27, "sloc": 26, "comments": 1, "multi": 0, "blank": 11, "single_comments": 2}, "fireeye.speakeasy/speakeasy/windows/kernel_mods/__init__.py": {"loc": 19, "lloc": 14, "sloc": 14, "comments": 3, "multi": 0, "blank": 4, "single_comments": 1}, "fireeye.speakeasy/speakeasy/winenv/arch.py": {"loc": 109, "lloc": 80, "sloc": 90, "comments": 9, "multi": 0, "blank": 12, "single_comments": 7}, "fireeye.speakeasy/speakeasy/winenv/__init__.py": {"loc": 0, "lloc": 0, "sloc": 0, "comments": 0, "multi": 0, "blank": 0, "single_comments": 0}, "fireeye.speakeasy/speakeasy/winenv/api/api.py": {"loc": 463, "lloc": 337, "sloc": 340, "comments": 9, "multi": 20, "blank": 94, "single_comments": 9}, "fireeye.speakeasy/speakeasy/winenv/api/winapi.py": {"loc": 83, "lloc": 61, "sloc": 59, "comments": 3, "multi": 6, "blank": 17, "single_comments": 1}, "fireeye.speakeasy/speakeasy/winenv/api/__init__.py": {"loc": 0, "lloc": 0, "sloc": 0, "comments": 0, "multi": 0, "blank": 0, "single_comments": 0}, "fireeye.speakeasy/speakeasy/winenv/api/kernelmode/fwpkclnt.py": {"loc": 368, "lloc": 212, "sloc": 197, "comments": 5, "multi": 83, "blank": 83, "single_comments": 5}, "fireeye.speakeasy/speakeasy/winenv/api/kernelmode/hal.py": {"loc": 54, "lloc": 28, "sloc": 24, "comments": 1, "multi": 17, "blank": 12, "single_comments": 1}, "fireeye.speakeasy/speakeasy/winenv/api/kernelmode/ndis.py": {"loc": 326, "lloc": 172, "sloc": 157, "comments": 1, "multi": 104, "blank": 64, "single_comments": 1}, "fireeye.speakeasy/speakeasy/winenv/api/kernelmode/netio.py": {"loc": 411, "lloc": 212, "sloc": 195, "comments": 21, "multi": 141, "blank": 71, "single_comments": 4}, "fireeye.speakeasy/speakeasy/winenv/api/kernelmode/ntoskrnl.py": {"loc": 3202, "lloc": 1692, "sloc": 1563, "comments": 42, "multi": 1061, "blank": 546, "single_comments": 32}, "fireeye.speakeasy/speakeasy/winenv/api/kernelmode/usbd.py": {"loc": 42, "lloc": 20, "sloc": 18, "comments": 1, "multi": 12, "blank": 11, "single_comments": 1}, "fireeye.speakeasy/speakeasy/winenv/api/kernelmode/wdfldr.py": {"loc": 880, "lloc": 513, "sloc": 503, "comments": 6, "multi": 202, "blank": 170, "single_comments": 5}, "fireeye.speakeasy/speakeasy/winenv/api/kernelmode/__init__.py": {"loc": 12, "lloc": 9, "sloc": 9, "comments": 0, "multi": 0, "blank": 3, "single_comments": 0}, "fireeye.speakeasy/speakeasy/winenv/api/usermode/advapi32.py": {"loc": 1201, "lloc": 652, "sloc": 625, "comments": 10, "multi": 356, "blank": 211, "single_comments": 9}, "fireeye.speakeasy/speakeasy/winenv/api/usermode/advpack.py": {"loc": 29, "lloc": 15, "sloc": 13, "comments": 1, "multi": 6, "blank": 9, "single_comments": 1}, "fireeye.speakeasy/speakeasy/winenv/api/usermode/bcrypt.py": {"loc": 148, "lloc": 75, "sloc": 75, "comments": 2, "multi": 43, "blank": 28, "single_comments": 2}, "fireeye.speakeasy/speakeasy/winenv/api/usermode/comctl32.py": {"loc": 32, "lloc": 18, "sloc": 17, "comments": 1, "multi": 5, "blank": 9, "single_comments": 1}, "fireeye.speakeasy/speakeasy/winenv/api/usermode/com_api.py": {"loc": 95, "lloc": 42, "sloc": 38, "comments": 6, "multi": 36, "blank": 15, "single_comments": 6}, "fireeye.speakeasy/speakeasy/winenv/api/usermode/crypt32.py": {"loc": 83, "lloc": 44, "sloc": 42, "comments": 2, "multi": 14, "blank": 25, "single_comments": 2}, "fireeye.speakeasy/speakeasy/winenv/api/usermode/dnsapi.py": {"loc": 95, "lloc": 62, "sloc": 61, "comments": 1, "multi": 10, "blank": 23, "single_comments": 1}, "fireeye.speakeasy/speakeasy/winenv/api/usermode/gdi32.py": {"loc": 241, "lloc": 89, "sloc": 70, "comments": 1, "multi": 143, "blank": 27, "single_comments": 1}, "fireeye.speakeasy/speakeasy/winenv/api/usermode/kernel32.py": {"loc": 5134, "lloc": 2928, "sloc": 2737, "comments": 66, "multi": 1426, "blank": 908, "single_comments": 63}, "fireeye.speakeasy/speakeasy/winenv/api/usermode/lz32.py": {"loc": 28, "lloc": 13, "sloc": 12, "comments": 1, "multi": 7, "blank": 8, "single_comments": 1}, "fireeye.speakeasy/speakeasy/winenv/api/usermode/mpr.py": {"loc": 88, "lloc": 41, "sloc": 37, "comments": 1, "multi": 32, "blank": 18, "single_comments": 1}, "fireeye.speakeasy/speakeasy/winenv/api/usermode/mscoree.py": {"loc": 33, "lloc": 15, "sloc": 13, "comments": 1, "multi": 8, "blank": 11, "single_comments": 1}, "fireeye.speakeasy/speakeasy/winenv/api/usermode/msi32.py": {"loc": 28, "lloc": 13, "sloc": 12, "comments": 1, "multi": 7, "blank": 8, "single_comments": 1}, "fireeye.speakeasy/speakeasy/winenv/api/usermode/msimg32.py": {"loc": 39, "lloc": 13, "sloc": 11, "comments": 1, "multi": 18, "blank": 9, "single_comments": 1}, "fireeye.speakeasy/speakeasy/winenv/api/usermode/msvcrt.py": {"loc": 1415, "lloc": 825, "sloc": 749, "comments": 12, "multi": 379, "blank": 269, "single_comments": 18}, "fireeye.speakeasy/speakeasy/winenv/api/usermode/ncrypt.py": {"loc": 120, "lloc": 64, "sloc": 64, "comments": 2, "multi": 33, "blank": 21, "single_comments": 2}, "fireeye.speakeasy/speakeasy/winenv/api/usermode/netapi32.py": {"loc": 115, "lloc": 67, "sloc": 63, "comments": 7, "multi": 22, "blank": 24, "single_comments": 6}, "fireeye.speakeasy/speakeasy/winenv/api/usermode/netutils.py": {"loc": 26, "lloc": 13, "sloc": 12, "comments": 1, "multi": 5, "blank": 8, "single_comments": 1}, "fireeye.speakeasy/speakeasy/winenv/api/usermode/ntdll.py": {"loc": 214, "lloc": 102, "sloc": 102, "comments": 3, "multi": 61, "blank": 46, "single_comments": 5}, "fireeye.speakeasy/speakeasy/winenv/api/usermode/ole32.py": {"loc": 169, "lloc": 85, "sloc": 77, "comments": 1, "multi": 59, "blank": 32, "single_comments": 1}, "fireeye.speakeasy/speakeasy/winenv/api/usermode/oleaut32.py": {"loc": 53, "lloc": 30, "sloc": 28, "comments": 2, "multi": 10, "blank": 13, "single_comments": 2}, "fireeye.speakeasy/speakeasy/winenv/api/usermode/secur32.py": {"loc": 47, "lloc": 26, "sloc": 25, "comments": 1, "multi": 7, "blank": 14, "single_comments": 1}, "fireeye.speakeasy/speakeasy/winenv/api/usermode/shell32.py": {"loc": 256, "lloc": 158, "sloc": 150, "comments": 35, "multi": 48, "blank": 36, "single_comments": 22}, "fireeye.speakeasy/speakeasy/winenv/api/usermode/shlwapi.py": {"loc": 266, "lloc": 175, "sloc": 156, "comments": 1, "multi": 61, "blank": 48, "single_comments": 1}, "fireeye.speakeasy/speakeasy/winenv/api/usermode/urlmon.py": {"loc": 55, "lloc": 32, "sloc": 31, "comments": 1, "multi": 9, "blank": 14, "single_comments": 1}, "fireeye.speakeasy/speakeasy/winenv/api/usermode/user32.py": {"loc": 1237, "lloc": 645, "sloc": 558, "comments": 8, "multi": 504, "blank": 168, "single_comments": 7}, "fireeye.speakeasy/speakeasy/winenv/api/usermode/winhttp.py": {"loc": 366, "lloc": 196, "sloc": 184, "comments": 5, "multi": 111, "blank": 67, "single_comments": 4}, "fireeye.speakeasy/speakeasy/winenv/api/usermode/wininet.py": {"loc": 411, "lloc": 236, "sloc": 224, "comments": 2, "multi": 118, "blank": 67, "single_comments": 2}, "fireeye.speakeasy/speakeasy/winenv/api/usermode/winmm.py": {"loc": 27, "lloc": 14, "sloc": 12, "comments": 0, "multi": 6, "blank": 9, "single_comments": 0}, "fireeye.speakeasy/speakeasy/winenv/api/usermode/wkscli.py": {"loc": 46, "lloc": 26, "sloc": 24, "comments": 2, "multi": 10, "blank": 10, "single_comments": 2}, "fireeye.speakeasy/speakeasy/winenv/api/usermode/ws2_32.py": {"loc": 697, "lloc": 407, "sloc": 379, "comments": 10, "multi": 176, "blank": 132, "single_comments": 10}, "fireeye.speakeasy/speakeasy/winenv/api/usermode/wtsapi32.py": {"loc": 92, "lloc": 51, "sloc": 49, "comments": 6, "multi": 14, "blank": 23, "single_comments": 6}, "fireeye.speakeasy/speakeasy/winenv/api/usermode/__init__.py": {"loc": 12, "lloc": 9, "sloc": 9, "comments": 0, "multi": 0, "blank": 3, "single_comments": 0}, "fireeye.speakeasy/speakeasy/winenv/decoys/__init__.py": {"loc": 0, "lloc": 0, "sloc": 0, "comments": 0, "multi": 0, "blank": 0, "single_comments": 0}, "fireeye.speakeasy/speakeasy/winenv/defs/usb.py": {"loc": 84, "lloc": 68, "sloc": 68, "comments": 1, "multi": 0, "blank": 15, "single_comments": 1}, "fireeye.speakeasy/speakeasy/winenv/defs/wdf.py": {"loc": 599, "lloc": 549, "sloc": 549, "comments": 1, "multi": 0, "blank": 49, "single_comments": 1}, "fireeye.speakeasy/speakeasy/winenv/defs/wininet.py": {"loc": 204, "lloc": 178, "sloc": 178, "comments": 1, "multi": 0, "blank": 25, "single_comments": 1}, "fireeye.speakeasy/speakeasy/winenv/defs/wsk.py": {"loc": 58, "lloc": 44, "sloc": 44, "comments": 1, "multi": 0, "blank": 13, "single_comments": 1}, "fireeye.speakeasy/speakeasy/winenv/defs/__init__.py": {"loc": 0, "lloc": 0, "sloc": 0, "comments": 0, "multi": 0, "blank": 0, "single_comments": 0}, "fireeye.speakeasy/speakeasy/winenv/defs/ndis/ndis.py": {"loc": 84, "lloc": 68, "sloc": 68, "comments": 1, "multi": 0, "blank": 15, "single_comments": 1}, "fireeye.speakeasy/speakeasy/winenv/defs/ndis/__init__.py": {"loc": 0, "lloc": 0, "sloc": 0, "comments": 0, "multi": 0, "blank": 0, "single_comments": 0}, "fireeye.speakeasy/speakeasy/winenv/defs/nt/ddk.py": {"loc": 236, "lloc": 194, "sloc": 197, "comments": 25, "multi": 0, "blank": 34, "single_comments": 5}, "fireeye.speakeasy/speakeasy/winenv/defs/nt/ntoskrnl.py": {"loc": 636, "lloc": 540, "sloc": 540, "comments": 8, "multi": 0, "blank": 95, "single_comments": 1}, "fireeye.speakeasy/speakeasy/winenv/defs/nt/__init__.py": {"loc": 0, "lloc": 0, "sloc": 0, "comments": 0, "multi": 0, "blank": 0, "single_comments": 0}, "fireeye.speakeasy/speakeasy/winenv/defs/registry/reg.py": {"loc": 86, "lloc": 63, "sloc": 63, "comments": 3, "multi": 0, "blank": 20, "single_comments": 3}, "fireeye.speakeasy/speakeasy/winenv/defs/registry/__init__.py": {"loc": 0, "lloc": 0, "sloc": 0, "comments": 0, "multi": 0, "blank": 0, "single_comments": 0}, "fireeye.speakeasy/speakeasy/winenv/defs/wfp/fwpmtypes.py": {"loc": 102, "lloc": 80, "sloc": 80, "comments": 1, "multi": 0, "blank": 21, "single_comments": 1}, "fireeye.speakeasy/speakeasy/winenv/defs/wfp/__init__.py": {"loc": 0, "lloc": 0, "sloc": 0, "comments": 0, "multi": 0, "blank": 0, "single_comments": 0}, "fireeye.speakeasy/speakeasy/winenv/defs/windows/advapi32.py": {"loc": 27, "lloc": 18, "sloc": 18, "comments": 1, "multi": 0, "blank": 8, "single_comments": 1}, "fireeye.speakeasy/speakeasy/winenv/defs/windows/com.py": {"loc": 155, "lloc": 116, "sloc": 119, "comments": 1, "multi": 0, "blank": 35, "single_comments": 1}, "fireeye.speakeasy/speakeasy/winenv/defs/windows/kernel32.py": {"loc": 235, "lloc": 194, "sloc": 194, "comments": 1, "multi": 0, "blank": 40, "single_comments": 1}, "fireeye.speakeasy/speakeasy/winenv/defs/windows/mpr.py": {"loc": 28, "lloc": 21, "sloc": 21, "comments": 1, "multi": 0, "blank": 6, "single_comments": 1}, "fireeye.speakeasy/speakeasy/winenv/defs/windows/netapi32.py": {"loc": 44, "lloc": 34, "sloc": 34, "comments": 1, "multi": 0, "blank": 9, "single_comments": 1}, "fireeye.speakeasy/speakeasy/winenv/defs/windows/secur32.py": {"loc": 26, "lloc": 21, "sloc": 21, "comments": 2, "multi": 0, "blank": 3, "single_comments": 2}, "fireeye.speakeasy/speakeasy/winenv/defs/windows/shell32.py": {"loc": 65, "lloc": 2, "sloc": 63, "comments": 0, "multi": 0, "blank": 2, "single_comments": 0}, "fireeye.speakeasy/speakeasy/winenv/defs/windows/user32.py": {"loc": 78, "lloc": 63, "sloc": 63, "comments": 1, "multi": 0, "blank": 14, "single_comments": 1}, "fireeye.speakeasy/speakeasy/winenv/defs/windows/windef.py": {"loc": 29, "lloc": 21, "sloc": 21, "comments": 1, "multi": 0, "blank": 7, "single_comments": 1}, "fireeye.speakeasy/speakeasy/winenv/defs/windows/windows.py": {"loc": 317, "lloc": 255, "sloc": 256, "comments": 4, "multi": 0, "blank": 57, "single_comments": 4}, "fireeye.speakeasy/speakeasy/winenv/defs/windows/__init__.py": {"loc": 0, "lloc": 0, "sloc": 0, "comments": 0, "multi": 0, "blank": 0, "single_comments": 0}, "fireeye.speakeasy/speakeasy/winenv/defs/winsock/winsock.py": {"loc": 82, "lloc": 56, "sloc": 56, "comments": 5, "multi": 0, "blank": 21, "single_comments": 5}, "fireeye.speakeasy/speakeasy/winenv/defs/winsock/ws2_32.py": {"loc": 58, "lloc": 45, "sloc": 45, "comments": 1, "multi": 0, "blank": 12, "single_comments": 1}, "fireeye.speakeasy/speakeasy/winenv/defs/winsock/__init__.py": {"loc": 0, "lloc": 0, "sloc": 0, "comments": 0, "multi": 0, "blank": 0, "single_comments": 0}, "fireeye.speakeasy/tests/test_argv.py": {"loc": 40, "lloc": 28, "sloc": 28, "comments": 1, "multi": 0, "blank": 11, "single_comments": 1}, "fireeye.speakeasy/tests/test_config.py": {"loc": 63, "lloc": 42, "sloc": 40, "comments": 4, "multi": 6, "blank": 13, "single_comments": 4}, "fireeye.speakeasy/tests/test_dlls.py": {"loc": 56, "lloc": 40, "sloc": 40, "comments": 1, "multi": 0, "blank": 15, "single_comments": 1}, "fireeye.speakeasy/tests/test_file_access.py": {"loc": 48, "lloc": 29, "sloc": 30, "comments": 1, "multi": 0, "blank": 17, "single_comments": 1}, "fireeye.speakeasy/tests/test_seh.py": {"loc": 59, "lloc": 36, "sloc": 42, "comments": 1, "multi": 0, "blank": 16, "single_comments": 1}, "fireeye.speakeasy/tests/test_struct.py": {"loc": 152, "lloc": 105, "sloc": 101, "comments": 14, "multi": 12, "blank": 26, "single_comments": 13}, "fireeye.speakeasy/tests/test_wdm.py": {"loc": 100, "lloc": 78, "sloc": 78, "comments": 1, "multi": 0, "blank": 21, "single_comments": 1}, "fireeye.speakeasy/tests/util.py": {"loc": 42, "lloc": 28, "sloc": 28, "comments": 1, "multi": 0, "blank": 13, "single_comments": 1}, "fireeye.speakeasy/tests/__init__.py": {"loc": 0, "lloc": 0, "sloc": 0, "comments": 0, "multi": 0, "blank": 0, "single_comments": 0}}
