{"joaoricardo000.whatsapp-bot-seed/src/config.py": {"loc": 65, "lloc": 12, "sloc": 16, "comments": 10, "multi": 24, "blank": 15, "single_comments": 10}, "joaoricardo000.whatsapp-bot-seed/src/router.py": {"loc": 93, "lloc": 53, "sloc": 48, "comments": 17, "multi": 11, "blank": 18, "single_comments": 16}, "joaoricardo000.whatsapp-bot-seed/src/server.py": {"loc": 56, "lloc": 38, "sloc": 35, "comments": 3, "multi": 6, "blank": 10, "single_comments": 5}, "joaoricardo000.whatsapp-bot-seed/src/__init__.py": {"loc": 1, "lloc": 1, "sloc": 1, "comments": 0, "multi": 0, "blank": 0, "single_comments": 0}, "joaoricardo000.whatsapp-bot-seed/src/layers/__init__.py": {"loc": 1, "lloc": 1, "sloc": 1, "comments": 0, "multi": 0, "blank": 0, "single_comments": 0}, "joaoricardo000.whatsapp-bot-seed/src/layers/notifications/notification_layer.py": {"loc": 93, "lloc": 44, "sloc": 43, "comments": 7, "multi": 28, "blank": 17, "single_comments": 5}, "joaoricardo000.whatsapp-bot-seed/src/layers/notifications/__init__.py": {"loc": 1, "lloc": 1, "sloc": 1, "comments": 0, "multi": 0, "blank": 0, "single_comments": 0}, "joaoricardo000.whatsapp-bot-seed/src/utils/media_sender.py": {"loc": 205, "lloc": 137, "sloc": 131, "comments": 1, "multi": 38, "blank": 34, "single_comments": 2}, "joaoricardo000.whatsapp-bot-seed/src/utils/session.py": {"loc": 29, "lloc": 19, "sloc": 18, "comments": 0, "multi": 6, "blank": 5, "single_comments": 0}, "joaoricardo000.whatsapp-bot-seed/src/utils/__init__.py": {"loc": 1, "lloc": 1, "sloc": 1, "comments": 0, "multi": 0, "blank": 0, "single_comments": 0}, "joaoricardo000.whatsapp-bot-seed/src/views/basic_views.py": {"loc": 9, "lloc": 5, "sloc": 5, "comments": 0, "multi": 0, "blank": 4, "single_comments": 0}, "joaoricardo000.whatsapp-bot-seed/src/views/bing.py": {"loc": 20, "lloc": 12, "sloc": 13, "comments": 0, "multi": 4, "blank": 3, "single_comments": 0}, "joaoricardo000.whatsapp-bot-seed/src/views/google.py": {"loc": 30, "lloc": 16, "sloc": 19, "comments": 0, "multi": 6, "blank": 5, "single_comments": 0}, "joaoricardo000.whatsapp-bot-seed/src/views/group_admin.py": {"loc": 80, "lloc": 42, "sloc": 40, "comments": 1, "multi": 29, "blank": 11, "single_comments": 0}, "joaoricardo000.whatsapp-bot-seed/src/views/media.py": {"loc": 41, "lloc": 23, "sloc": 26, "comments": 0, "multi": 7, "blank": 8, "single_comments": 0}, "joaoricardo000.whatsapp-bot-seed/src/views/quiz.py": {"loc": 74, "lloc": 39, "sloc": 43, "comments": 4, "multi": 18, "blank": 10, "single_comments": 3}, "joaoricardo000.whatsapp-bot-seed/src/views/super_views.py": {"loc": 57, "lloc": 23, "sloc": 47, "comments": 0, "multi": 0, "blank": 10, "single_comments": 0}, "joaoricardo000.whatsapp-bot-seed/src/views/__init__.py": {"loc": 1, "lloc": 1, "sloc": 1, "comments": 0, "multi": 0, "blank": 0, "single_comments": 0}}
