{"psf/black/fuzz.py": {"loc": 85, "lloc": 31, "sloc": 52, "comments": 26, "multi": 5, "blank": 12, "single_comments": 16}, "psf/black/setup.py": {"loc": 108, "lloc": 24, "sloc": 96, "comments": 4, "multi": 0, "blank": 10, "single_comments": 2}, "psf/black/docs/conf.py": {"loc": 427, "lloc": 182, "sloc": 225, "comments": 96, "multi": 32, "blank": 86, "single_comments": 84}, "psf/black/gallery/gallery.py": {"loc": 307, "lloc": 158, "sloc": 244, "comments": 7, "multi": 0, "blank": 60, "single_comments": 3}, "psf/black/profiling/dict_big.py": {"loc": 8001, "lloc": 2, "sloc": 8001, "comments": 0, "multi": 0, "blank": 0, "single_comments": 0}, "psf/black/profiling/dict_huge.py": {"loc": 41440, "lloc": 2, "sloc": 41440, "comments": 0, "multi": 0, "blank": 0, "single_comments": 0}, "psf/black/profiling/list_big.py": {"loc": 4000, "lloc": 1, "sloc": 4000, "comments": 0, "multi": 0, "blank": 0, "single_comments": 0}, "psf/black/profiling/list_huge.py": {"loc": 22431, "lloc": 1, "sloc": 22431, "comments": 0, "multi": 0, "blank": 0, "single_comments": 0}, "psf/black/profiling/mix_big.py": {"loc": 1002, "lloc": 2, "sloc": 1002, "comments": 0, "multi": 0, "blank": 0, "single_comments": 0}, "psf/black/profiling/mix_huge.py": {"loc": 7692, "lloc": 2, "sloc": 7692, "comments": 0, "multi": 0, "blank": 0, "single_comments": 0}, "psf/black/profiling/mix_small.py": {"loc": 102, "lloc": 2, "sloc": 102, "comments": 0, "multi": 0, "blank": 0, "single_comments": 0}, "psf/black/src/black/__init__.py": {"loc": 6977, "lloc": 3508, "sloc": 4342, "comments": 472, "multi": 951, "blank": 1196, "single_comments": 488}, "psf/black/src/black/__main__.py": {"loc": 3, "lloc": 2, "sloc": 2, "comments": 0, "multi": 0, "blank": 1, "single_comments": 0}, "psf/black/src/blackd/__init__.py": {"loc": 211, "lloc": 132, "sloc": 178, "comments": 5, "multi": 0, "blank": 28, "single_comments": 5}, "psf/black/src/black_primer/cli.py": {"loc": 136, "lloc": 55, "sloc": 114, "comments": 4, "multi": 0, "blank": 17, "single_comments": 5}, "psf/black/src/black_primer/lib.py": {"loc": 337, "lloc": 190, "sloc": 246, "comments": 20, "multi": 14, "blank": 56, "single_comments": 21}, "psf/black/src/blib2to3/pygram.py": {"loc": 197, "lloc": 260, "sloc": 153, "comments": 14, "multi": 4, "blank": 25, "single_comments": 15}, "psf/black/src/blib2to3/pytree.py": {"loc": 980, "lloc": 571, "sloc": 554, "comments": 40, "multi": 213, "blank": 165, "single_comments": 48}, "psf/black/src/blib2to3/__init__.py": {"loc": 1, "lloc": 0, "sloc": 0, "comments": 1, "multi": 0, "blank": 0, "single_comments": 1}, "psf/black/src/blib2to3/pgen2/conv.py": {"loc": 256, "lloc": 167, "sloc": 161, "comments": 13, "multi": 51, "blank": 31, "single_comments": 13}, "psf/black/src/blib2to3/pgen2/driver.py": {"loc": 253, "lloc": 175, "sloc": 188, "comments": 11, "multi": 14, "blank": 33, "single_comments": 18}, "psf/black/src/blib2to3/pgen2/grammar.py": {"loc": 223, "lloc": 84, "sloc": 125, "comments": 10, "multi": 50, "blank": 35, "single_comments": 13}, "psf/black/src/blib2to3/pgen2/literals.py": {"loc": 68, "lloc": 47, "sloc": 52, "comments": 2, "multi": 0, "blank": 13, "single_comments": 3}, "psf/black/src/blib2to3/pgen2/parse.py": {"loc": 235, "lloc": 115, "sloc": 114, "comments": 22, "multi": 56, "blank": 38, "single_comments": 27}, "psf/black/src/blib2to3/pgen2/pgen.py": {"loc": 428, "lloc": 345, "sloc": 349, "comments": 44, "multi": 0, "blank": 44, "single_comments": 35}, "psf/black/src/blib2to3/pgen2/token.py": {"loc": 94, "lloc": 142, "sloc": 78, "comments": 4, "multi": 0, "blank": 11, "single_comments": 5}, "psf/black/src/blib2to3/pgen2/tokenize.py": {"loc": 681, "lloc": 400, "sloc": 480, "comments": 41, "multi": 71, "blank": 109, "single_comments": 21}, "psf/black/src/blib2to3/pgen2/__init__.py": {"loc": 4, "lloc": 1, "sloc": 0, "comments": 2, "multi": 0, "blank": 1, "single_comments": 3}, "psf/black/tests/test_black.py": {"loc": 1917, "lloc": 1277, "sloc": 1699, "comments": 62, "multi": 5, "blank": 155, "single_comments": 58}, "psf/black/tests/test_blackd.py": {"loc": 192, "lloc": 142, "sloc": 165, "comments": 2, "multi": 0, "blank": 25, "single_comments": 2}, "psf/black/tests/test_format.py": {"loc": 103, "lloc": 25, "sloc": 95, "comments": 0, "multi": 0, "blank": 8, "single_comments": 0}, "psf/black/tests/test_primer.py": {"loc": 216, "lloc": 132, "sloc": 166, "comments": 6, "multi": 0, "blank": 43, "single_comments": 7}, "psf/black/tests/util.py": {"loc": 83, "lloc": 71, "sloc": 66, "comments": 1, "multi": 0, "blank": 15, "single_comments": 2}, "psf/black/tests/__init__.py": {"loc": 0, "lloc": 0, "sloc": 0, "comments": 0, "multi": 0, "blank": 0, "single_comments": 0}, "psf/black/tests/data/async_as_identifier.py": {"loc": 49, "lloc": 38, "sloc": 30, "comments": 1, "multi": 0, "blank": 18, "single_comments": 1}, "psf/black/tests/data/beginning_backslash.py": {"loc": 12, "lloc": 2, "sloc": 3, "comments": 1, "multi": 0, "blank": 8, "single_comments": 1}, "psf/black/tests/data/blackd_diff.py": {"loc": 6, "lloc": 3, "sloc": 5, "comments": 0, "multi": 0, "blank": 1, "single_comments": 0}, "psf/black/tests/data/bracketmatch.py": {"loc": 15, "lloc": 12, "sloc": 10, "comments": 1, "multi": 0, "blank": 4, "single_comments": 1}, "psf/black/tests/data/cantfit.py": {"loc": 107, "lloc": 32, "sloc": 96, "comments": 11, "multi": 0, "blank": 4, "single_comments": 7}, "psf/black/tests/data/class_blank_parentheses.py": {"loc": 58, "lloc": 38, "sloc": 39, "comments": 1, "multi": 0, "blank": 18, "single_comments": 1}, "psf/black/tests/data/class_methods_new_line.py": {"loc": 270, "lloc": 200, "sloc": 182, "comments": 1, "multi": 0, "blank": 69, "single_comments": 19}, "psf/black/tests/data/collections.py": {"loc": 174, "lloc": 78, "sloc": 142, "comments": 9, "multi": 0, "blank": 23, "single_comments": 9}, "psf/black/tests/data/comments.py": {"loc": 96, "lloc": 37, "sloc": 34, "comments": 31, "multi": 6, "blank": 28, "single_comments": 28}, "psf/black/tests/data/comments2.py": {"loc": 342, "lloc": 66, "sloc": 268, "comments": 104, "multi": 0, "blank": 41, "single_comments": 33}, "psf/black/tests/data/comments3.py": {"loc": 47, "lloc": 9, "sloc": 38, "comments": 14, "multi": 0, "blank": 4, "single_comments": 5}, "psf/black/tests/data/comments4.py": {"loc": 94, "lloc": 15, "sloc": 85, "comments": 9, "multi": 0, "blank": 8, "single_comments": 1}, "psf/black/tests/data/comments5.py": {"loc": 71, "lloc": 31, "sloc": 31, "comments": 21, "multi": 0, "blank": 20, "single_comments": 20}, "psf/black/tests/data/comments6.py": {"loc": 118, "lloc": 28, "sloc": 87, "comments": 43, "multi": 0, "blank": 25, "single_comments": 6}, "psf/black/tests/data/comments7.py": {"loc": 266, "lloc": 36, "sloc": 235, "comments": 43, "multi": 0, "blank": 26, "single_comments": 5}, "psf/black/tests/data/comment_after_escaped_newline.py": {"loc": 18, "lloc": 8, "sloc": 11, "comments": 5, "multi": 0, "blank": 6, "single_comments": 1}, "psf/black/tests/data/composition.py": {"loc": 181, "lloc": 38, "sloc": 171, "comments": 5, "multi": 0, "blank": 10, "single_comments": 0}, "psf/black/tests/data/composition_no_trailing_comma.py": {"loc": 367, "lloc": 76, "sloc": 342, "comments": 11, "multi": 0, "blank": 24, "single_comments": 1}, "psf/black/tests/data/debug_visitor.py": {"loc": 32, "lloc": 26, "sloc": 23, "comments": 2, "multi": 3, "blank": 4, "single_comments": 2}, "psf/black/tests/data/decorators.py": {"loc": 176, "lloc": 84, "sloc": 84, "comments": 35, "multi": 0, "blank": 57, "single_comments": 35}, "psf/black/tests/data/docstring.py": {"loc": 276, "lloc": 98, "sloc": 61, "comments": 1, "multi": 128, "blank": 83, "single_comments": 4}, "psf/black/tests/data/docstring_no_string_normalization.py": {"loc": 209, "lloc": 84, "sloc": 53, "comments": 1, "multi": 88, "blank": 62, "single_comments": 6}, "psf/black/tests/data/empty_lines.py": {"loc": 187, "lloc": 88, "sloc": 122, "comments": 21, "multi": 0, "blank": 46, "single_comments": 19}, "psf/black/tests/data/expression.py": {"loc": 630, "lloc": 528, "sloc": 611, "comments": 11, "multi": 0, "blank": 12, "single_comments": 7}, "psf/black/tests/data/fmtonoff.py": {"loc": 413, "lloc": 158, "sloc": 277, "comments": 77, "multi": 6, "blank": 51, "single_comments": 79}, "psf/black/tests/data/fmtonoff2.py": {"loc": 40, "lloc": 15, "sloc": 23, "comments": 7, "multi": 0, "blank": 11, "single_comments": 6}, "psf/black/tests/data/fmtonoff3.py": {"loc": 35, "lloc": 6, "sloc": 20, "comments": 9, "multi": 0, "blank": 6, "single_comments": 9}, "psf/black/tests/data/fmtonoff4.py": {"loc": 36, "lloc": 12, "sloc": 26, "comments": 5, "multi": 0, "blank": 5, "single_comments": 5}, "psf/black/tests/data/fmtskip.py": {"loc": 3, "lloc": 3, "sloc": 3, "comments": 1, "multi": 0, "blank": 0, "single_comments": 0}, "psf/black/tests/data/fmtskip2.py": {"loc": 17, "lloc": 6, "sloc": 14, "comments": 3, "multi": 0, "blank": 2, "single_comments": 1}, "psf/black/tests/data/fmtskip3.py": {"loc": 20, "lloc": 10, "sloc": 13, "comments": 7, "multi": 0, "blank": 2, "single_comments": 5}, "psf/black/tests/data/fmtskip4.py": {"loc": 13, "lloc": 4, "sloc": 8, "comments": 3, "multi": 0, "blank": 2, "single_comments": 3}, "psf/black/tests/data/fmtskip5.py": {"loc": 22, "lloc": 10, "sloc": 18, "comments": 3, "multi": 0, "blank": 3, "single_comments": 1}, "psf/black/tests/data/force_py36.py": {"loc": 16, "lloc": 4, "sloc": 11, "comments": 5, "multi": 0, "blank": 0, "single_comments": 5}, "psf/black/tests/data/force_pyi.py": {"loc": 65, "lloc": 68, "sloc": 43, "comments": 1, "multi": 0, "blank": 21, "single_comments": 1}, "psf/black/tests/data/fstring.py": {"loc": 21, "lloc": 18, "sloc": 0, "comments": 1, "multi": 0, "blank": 2, "single_comments": 19}, "psf/black/tests/data/function.py": {"loc": 247, "lloc": 102, "sloc": 209, "comments": 6, "multi": 0, "blank": 30, "single_comments": 8}, "psf/black/tests/data/function2.py": {"loc": 58, "lloc": 30, "sloc": 46, "comments": 3, "multi": 0, "blank": 9, "single_comments": 3}, "psf/black/tests/data/function_trailing_comma.py": {"loc": 88, "lloc": 38, "sloc": 76, "comments": 1, "multi": 0, "blank": 11, "single_comments": 1}, "psf/black/tests/data/import_spacing.py": {"loc": 118, "lloc": 42, "sloc": 91, "comments": 11, "multi": 0, "blank": 20, "single_comments": 7}, "psf/black/tests/data/long_strings.py": {"loc": 589, "lloc": 134, "sloc": 472, "comments": 25, "multi": 0, "blank": 114, "single_comments": 3}, "psf/black/tests/data/long_strings_flag_disabled.py": {"loc": 289, "lloc": 67, "sloc": 232, "comments": 12, "multi": 0, "blank": 56, "single_comments": 1}, "psf/black/tests/data/long_strings__edge_case.py": {"loc": 110, "lloc": 38, "sloc": 105, "comments": 1, "multi": 0, "blank": 4, "single_comments": 1}, "psf/black/tests/data/long_strings__regression.py": {"loc": 888, "lloc": 242, "sloc": 737, "comments": 59, "multi": 0, "blank": 138, "single_comments": 13}, "psf/black/tests/data/missing_final_newline.py": {"loc": 3, "lloc": 0, "sloc": 0, "comments": 3, "multi": 0, "blank": 0, "single_comments": 3}, "psf/black/tests/data/numeric_literals.py": {"loc": 44, "lloc": 36, "sloc": 36, "comments": 3, "multi": 0, "blank": 5, "single_comments": 3}, "psf/black/tests/data/numeric_literals_py2.py": {"loc": 16, "lloc": 8, "sloc": 8, "comments": 3, "multi": 0, "blank": 5, "single_comments": 3}, "psf/black/tests/data/numeric_literals_skip_underscores.py": {"loc": 23, "lloc": 16, "sloc": 16, "comments": 3, "multi": 0, "blank": 4, "single_comments": 3}, "psf/black/tests/data/pep_570.py": {"loc": 44, "lloc": 18, "sloc": 31, "comments": 0, "multi": 0, "blank": 13, "single_comments": 0}, "psf/black/tests/data/pep_572.py": {"loc": 47, "lloc": 44, "sloc": 40, "comments": 0, "multi": 0, "blank": 7, "single_comments": 0}, "psf/black/tests/data/pep_572_remove_parens.py": {"loc": 38, "lloc": 24, "sloc": 22, "comments": 1, "multi": 0, "blank": 15, "single_comments": 1}, "psf/black/tests/data/percent_precedence.py": {"loc": 41, "lloc": 38, "sloc": 38, "comments": 1, "multi": 0, "blank": 2, "single_comments": 1}, "psf/black/tests/data/python2.py": {"error": "SyntaxError at line: 7"}, "psf/black/tests/data/python2_print_function.py": {"loc": 16, "lloc": 8, "sloc": 8, "comments": 3, "multi": 0, "blank": 5, "single_comments": 3}, "psf/black/tests/data/python2_unicode_literals.py": {"loc": 20, "lloc": 12, "sloc": 7, "comments": 3, "multi": 0, "blank": 5, "single_comments": 8}, "psf/black/tests/data/python37.py": {"loc": 65, "lloc": 22, "sloc": 38, "comments": 3, "multi": 0, "blank": 24, "single_comments": 3}, "psf/black/tests/data/python38.py": {"loc": 45, "lloc": 26, "sloc": 20, "comments": 7, "multi": 0, "blank": 18, "single_comments": 7}, "psf/black/tests/data/python39.py": {"loc": 37, "lloc": 18, "sloc": 22, "comments": 3, "multi": 0, "blank": 12, "single_comments": 3}, "psf/black/tests/data/remove_parens.py": {"loc": 142, "lloc": 64, "sloc": 96, "comments": 1, "multi": 0, "blank": 45, "single_comments": 1}, "psf/black/tests/data/slices.py": {"loc": 31, "lloc": 47, "sloc": 25, "comments": 2, "multi": 0, "blank": 4, "single_comments": 2}, "psf/black/tests/data/string_prefixes.py": {"loc": 18, "lloc": 10, "sloc": 2, "comments": 3, "multi": 0, "blank": 5, "single_comments": 11}, "psf/black/tests/data/string_quotes.py": {"loc": 102, "lloc": 92, "sloc": 2, "comments": 1, "multi": 10, "blank": 2, "single_comments": 88}, "psf/black/tests/data/trailing_comma_optional_parens1.py": {"loc": 3, "lloc": 2, "sloc": 3, "comments": 0, "multi": 0, "blank": 0, "single_comments": 0}, "psf/black/tests/data/trailing_comma_optional_parens2.py": {"loc": 3, "lloc": 2, "sloc": 3, "comments": 0, "multi": 0, "blank": 0, "single_comments": 0}, "psf/black/tests/data/trailing_comma_optional_parens3.py": {"loc": 8, "lloc": 5, "sloc": 8, "comments": 0, "multi": 0, "blank": 0, "single_comments": 0}, "psf/black/tests/data/tricky_unicode_symbols.py": {"error": "SyntaxError at line: 4"}, "psf/black/tests/data/tupleassign.py": {"loc": 23, "lloc": 6, "sloc": 11, "comments": 5, "multi": 0, "blank": 7, "single_comments": 5}, "psf/black/tests/data/include_exclude_tests/b/dont_exclude/a.py": {"loc": 0, "lloc": 0, "sloc": 0, "comments": 0, "multi": 0, "blank": 0, "single_comments": 0}, "psf/black/tests/data/include_exclude_tests/b/exclude/a.py": {"loc": 0, "lloc": 0, "sloc": 0, "comments": 0, "multi": 0, "blank": 0, "single_comments": 0}}
