{"yogeshojha.rengine/manage.py": {"loc": 21, "lloc": 12, "sloc": 15, "comments": 1, "multi": 0, "blank": 4, "single_comments": 2}, "yogeshojha.rengine/dashboard/admin.py": {"loc": 3, "lloc": 1, "sloc": 1, "comments": 1, "multi": 0, "blank": 1, "single_comments": 1}, "yogeshojha.rengine/dashboard/apps.py": {"loc": 5, "lloc": 3, "sloc": 3, "comments": 0, "multi": 0, "blank": 2, "single_comments": 0}, "yogeshojha.rengine/dashboard/models.py": {"loc": 3, "lloc": 1, "sloc": 1, "comments": 1, "multi": 0, "blank": 1, "single_comments": 1}, "yogeshojha.rengine/dashboard/tests.py": {"loc": 3, "lloc": 1, "sloc": 1, "comments": 1, "multi": 0, "blank": 1, "single_comments": 1}, "yogeshojha.rengine/dashboard/urls.py": {"loc": 15, "lloc": 4, "sloc": 13, "comments": 0, "multi": 0, "blank": 2, "single_comments": 0}, "yogeshojha.rengine/dashboard/views.py": {"loc": 184, "lloc": 107, "sloc": 162, "comments": 6, "multi": 0, "blank": 16, "single_comments": 6}, "yogeshojha.rengine/dashboard/__init__.py": {"loc": 0, "lloc": 0, "sloc": 0, "comments": 0, "multi": 0, "blank": 0, "single_comments": 0}, "yogeshojha.rengine/notification/admin.py": {"loc": 4, "lloc": 3, "sloc": 3, "comments": 1, "multi": 0, "blank": 0, "single_comments": 1}, "yogeshojha.rengine/notification/apps.py": {"loc": 5, "lloc": 3, "sloc": 3, "comments": 0, "multi": 0, "blank": 2, "single_comments": 0}, "yogeshojha.rengine/notification/forms.py": {"loc": 62, "lloc": 21, "sloc": 55, "comments": 0, "multi": 0, "blank": 7, "single_comments": 0}, "yogeshojha.rengine/notification/models.py": {"loc": 10, "lloc": 7, "sloc": 7, "comments": 0, "multi": 0, "blank": 3, "single_comments": 0}, "yogeshojha.rengine/notification/tests.py": {"loc": 3, "lloc": 1, "sloc": 1, "comments": 1, "multi": 0, "blank": 1, "single_comments": 1}, "yogeshojha.rengine/notification/urls.py": {"loc": 22, "lloc": 4, "sloc": 21, "comments": 0, "multi": 0, "blank": 1, "single_comments": 0}, "yogeshojha.rengine/notification/views.py": {"loc": 88, "lloc": 59, "sloc": 78, "comments": 0, "multi": 0, "blank": 10, "single_comments": 0}, "yogeshojha.rengine/notification/__init__.py": {"loc": 0, "lloc": 0, "sloc": 0, "comments": 0, "multi": 0, "blank": 0, "single_comments": 0}, "yogeshojha.rengine/notification/migrations/0001_initial.py": {"loc": 23, "lloc": 5, "sloc": 16, "comments": 1, "multi": 0, "blank": 6, "single_comments": 1}, "yogeshojha.rengine/notification/migrations/__init__.py": {"loc": 0, "lloc": 0, "sloc": 0, "comments": 0, "multi": 0, "blank": 0, "single_comments": 0}, "yogeshojha.rengine/reNgine/celery.py": {"loc": 9, "lloc": 6, "sloc": 6, "comments": 0, "multi": 0, "blank": 3, "single_comments": 0}, "yogeshojha.rengine/reNgine/definitions.py": {"loc": 55, "lloc": 29, "sloc": 29, "comments": 16, "multi": 0, "blank": 10, "single_comments": 16}, "yogeshojha.rengine/reNgine/init.py": {"loc": 35, "lloc": 24, "sloc": 23, "comments": 0, "multi": 4, "blank": 8, "single_comments": 0}, "yogeshojha.rengine/reNgine/settings.py": {"loc": 166, "lloc": 43, "sloc": 121, "comments": 10, "multi": 3, "blank": 32, "single_comments": 10}, "yogeshojha.rengine/reNgine/tasks.py": {"loc": 797, "lloc": 496, "sloc": 566, "comments": 66, "multi": 60, "blank": 109, "single_comments": 62}, "yogeshojha.rengine/reNgine/urls.py": {"loc": 36, "lloc": 6, "sloc": 34, "comments": 0, "multi": 0, "blank": 2, "single_comments": 0}, "yogeshojha.rengine/reNgine/validators.py": {"loc": 24, "lloc": 17, "sloc": 18, "comments": 0, "multi": 0, "blank": 6, "single_comments": 0}, "yogeshojha.rengine/reNgine/wsgi.py": {"loc": 16, "lloc": 5, "sloc": 4, "comments": 0, "multi": 6, "blank": 6, "single_comments": 0}, "yogeshojha.rengine/reNgine/__init__.py": {"loc": 3, "lloc": 2, "sloc": 2, "comments": 0, "multi": 0, "blank": 1, "single_comments": 0}, "yogeshojha.rengine/scanEngine/admin.py": {"loc": 7, "lloc": 5, "sloc": 5, "comments": 1, "multi": 0, "blank": 1, "single_comments": 1}, "yogeshojha.rengine/scanEngine/apps.py": {"loc": 5, "lloc": 3, "sloc": 3, "comments": 0, "multi": 0, "blank": 2, "single_comments": 0}, "yogeshojha.rengine/scanEngine/forms.py": {"loc": 142, "lloc": 60, "sloc": 132, "comments": 0, "multi": 0, "blank": 10, "single_comments": 0}, "yogeshojha.rengine/scanEngine/models.py": {"loc": 42, "lloc": 27, "sloc": 32, "comments": 0, "multi": 0, "blank": 10, "single_comments": 0}, "yogeshojha.rengine/scanEngine/tests.py": {"loc": 3, "lloc": 1, "sloc": 1, "comments": 1, "multi": 0, "blank": 1, "single_comments": 1}, "yogeshojha.rengine/scanEngine/urls.py": {"loc": 51, "lloc": 4, "sloc": 49, "comments": 0, "multi": 0, "blank": 2, "single_comments": 0}, "yogeshojha.rengine/scanEngine/views.py": {"loc": 194, "lloc": 130, "sloc": 172, "comments": 0, "multi": 0, "blank": 22, "single_comments": 0}, "yogeshojha.rengine/scanEngine/__init__.py": {"loc": 0, "lloc": 0, "sloc": 0, "comments": 0, "multi": 0, "blank": 0, "single_comments": 0}, "yogeshojha.rengine/scanEngine/migrations/0001_initial.py": {"loc": 28, "lloc": 5, "sloc": 21, "comments": 1, "multi": 0, "blank": 6, "single_comments": 1}, "yogeshojha.rengine/scanEngine/migrations/0002_auto_20200717_1414.py": {"loc": 18, "lloc": 4, "sloc": 12, "comments": 1, "multi": 0, "blank": 5, "single_comments": 1}, "yogeshojha.rengine/scanEngine/migrations/0003_wordlist.py": {"loc": 22, "lloc": 4, "sloc": 16, "comments": 1, "multi": 0, "blank": 5, "single_comments": 1}, "yogeshojha.rengine/scanEngine/migrations/0004_wordlist_short_name.py": {"loc": 19, "lloc": 4, "sloc": 13, "comments": 1, "multi": 0, "blank": 5, "single_comments": 1}, "yogeshojha.rengine/scanEngine/migrations/0005_auto_20200718_0407.py": {"loc": 18, "lloc": 4, "sloc": 12, "comments": 1, "multi": 0, "blank": 5, "single_comments": 1}, "yogeshojha.rengine/scanEngine/migrations/0006_auto_20200718_0429.py": {"loc": 18, "lloc": 4, "sloc": 12, "comments": 1, "multi": 0, "blank": 5, "single_comments": 1}, "yogeshojha.rengine/scanEngine/migrations/0007_remove_wordlist_path.py": {"loc": 17, "lloc": 4, "sloc": 11, "comments": 1, "multi": 0, "blank": 5, "single_comments": 1}, "yogeshojha.rengine/scanEngine/migrations/0008_configuration.py": {"loc": 22, "lloc": 4, "sloc": 16, "comments": 1, "multi": 0, "blank": 5, "single_comments": 1}, "yogeshojha.rengine/scanEngine/migrations/0009_auto_20200725_1822.py": {"loc": 23, "lloc": 4, "sloc": 17, "comments": 1, "multi": 0, "blank": 5, "single_comments": 1}, "yogeshojha.rengine/scanEngine/migrations/0010_enginetype_vulnerability_scan.py": {"loc": 18, "lloc": 4, "sloc": 12, "comments": 1, "multi": 0, "blank": 5, "single_comments": 1}, "yogeshojha.rengine/scanEngine/migrations/0011_remove_enginetype_subdomain_takeover.py": {"loc": 17, "lloc": 4, "sloc": 11, "comments": 1, "multi": 0, "blank": 5, "single_comments": 1}, "yogeshojha.rengine/scanEngine/migrations/__init__.py": {"loc": 0, "lloc": 0, "sloc": 0, "comments": 0, "multi": 0, "blank": 0, "single_comments": 0}, "yogeshojha.rengine/startScan/admin.py": {"loc": 9, "lloc": 7, "sloc": 8, "comments": 0, "multi": 0, "blank": 1, "single_comments": 0}, "yogeshojha.rengine/startScan/apps.py": {"loc": 5, "lloc": 3, "sloc": 3, "comments": 0, "multi": 0, "blank": 2, "single_comments": 0}, "yogeshojha.rengine/startScan/models.py": {"loc": 81, "lloc": 64, "sloc": 64, "comments": 1, "multi": 0, "blank": 16, "single_comments": 1}, "yogeshojha.rengine/startScan/tests.py": {"loc": 3, "lloc": 1, "sloc": 1, "comments": 1, "multi": 0, "blank": 1, "single_comments": 1}, "yogeshojha.rengine/startScan/urls.py": {"loc": 91, "lloc": 4, "sloc": 90, "comments": 0, "multi": 0, "blank": 1, "single_comments": 0}, "yogeshojha.rengine/startScan/views.py": {"loc": 388, "lloc": 246, "sloc": 329, "comments": 15, "multi": 4, "blank": 40, "single_comments": 15}, "yogeshojha.rengine/startScan/__init__.py": {"loc": 0, "lloc": 0, "sloc": 0, "comments": 0, "multi": 0, "blank": 0, "single_comments": 0}, "yogeshojha.rengine/startScan/api/serializers.py": {"loc": 44, "lloc": 29, "sloc": 29, "comments": 1, "multi": 0, "blank": 14, "single_comments": 1}, "yogeshojha.rengine/startScan/api/urls.py": {"loc": 20, "lloc": 11, "sloc": 13, "comments": 0, "multi": 0, "blank": 7, "single_comments": 0}, "yogeshojha.rengine/startScan/api/views.py": {"loc": 487, "lloc": 412, "sloc": 461, "comments": 7, "multi": 0, "blank": 19, "single_comments": 7}, "yogeshojha.rengine/startScan/api/__init__.py": {"loc": 0, "lloc": 0, "sloc": 0, "comments": 0, "multi": 0, "blank": 0, "single_comments": 0}, "yogeshojha.rengine/startScan/migrations/0001_initial.py": {"loc": 68, "lloc": 7, "sloc": 61, "comments": 1, "multi": 0, "blank": 6, "single_comments": 1}, "yogeshojha.rengine/startScan/migrations/0002_scanhistory_celery_id.py": {"loc": 18, "lloc": 4, "sloc": 12, "comments": 1, "multi": 0, "blank": 5, "single_comments": 1}, "yogeshojha.rengine/startScan/migrations/0003_waybackendpoint_content_type.py": {"loc": 18, "lloc": 4, "sloc": 12, "comments": 1, "multi": 0, "blank": 5, "single_comments": 1}, "yogeshojha.rengine/startScan/migrations/0004_scannedhost_is_ip_cdn.py": {"loc": 18, "lloc": 4, "sloc": 12, "comments": 1, "multi": 0, "blank": 5, "single_comments": 1}, "yogeshojha.rengine/startScan/migrations/0005_scannedhost_cname.py": {"loc": 18, "lloc": 4, "sloc": 12, "comments": 1, "multi": 0, "blank": 5, "single_comments": 1}, "yogeshojha.rengine/startScan/migrations/0006_vulnerabilityscanner.py": {"loc": 28, "lloc": 5, "sloc": 22, "comments": 1, "multi": 0, "blank": 5, "single_comments": 1}, "yogeshojha.rengine/startScan/migrations/0007_auto_20201010_1546.py": {"loc": 17, "lloc": 4, "sloc": 11, "comments": 1, "multi": 0, "blank": 5, "single_comments": 1}, "yogeshojha.rengine/startScan/migrations/0008_auto_20201010_1555.py": {"loc": 18, "lloc": 4, "sloc": 12, "comments": 1, "multi": 0, "blank": 5, "single_comments": 1}, "yogeshojha.rengine/startScan/migrations/0009_auto_20201010_1631.py": {"loc": 28, "lloc": 4, "sloc": 22, "comments": 1, "multi": 0, "blank": 5, "single_comments": 1}, "yogeshojha.rengine/startScan/migrations/0010_vulnerabilityscan_discovered_date.py": {"loc": 18, "lloc": 4, "sloc": 12, "comments": 1, "multi": 0, "blank": 5, "single_comments": 1}, "yogeshojha.rengine/startScan/migrations/0011_vulnerabilityscan_host.py": {"loc": 19, "lloc": 5, "sloc": 13, "comments": 1, "multi": 0, "blank": 5, "single_comments": 1}, "yogeshojha.rengine/startScan/migrations/0012_remove_scannedhost_takeover.py": {"loc": 17, "lloc": 4, "sloc": 11, "comments": 1, "multi": 0, "blank": 5, "single_comments": 1}, "yogeshojha.rengine/startScan/migrations/0013_vulnerabilityscan_status.py": {"loc": 18, "lloc": 4, "sloc": 12, "comments": 1, "multi": 0, "blank": 5, "single_comments": 1}, "yogeshojha.rengine/startScan/migrations/0014_auto_20201121_1637.py": {"loc": 22, "lloc": 4, "sloc": 16, "comments": 1, "multi": 0, "blank": 5, "single_comments": 1}, "yogeshojha.rengine/startScan/migrations/0015_scannedhost_checked.py": {"loc": 18, "lloc": 4, "sloc": 12, "comments": 1, "multi": 0, "blank": 5, "single_comments": 1}, "yogeshojha.rengine/startScan/migrations/0016_scannedhost_date_discovered.py": {"loc": 19, "lloc": 5, "sloc": 13, "comments": 1, "multi": 0, "blank": 5, "single_comments": 1}, "yogeshojha.rengine/startScan/migrations/0017_auto_20201126_1018.py": {"loc": 18, "lloc": 4, "sloc": 12, "comments": 1, "multi": 0, "blank": 5, "single_comments": 1}, "yogeshojha.rengine/startScan/migrations/0018_auto_20201126_1026.py": {"loc": 18, "lloc": 4, "sloc": 12, "comments": 1, "multi": 0, "blank": 5, "single_comments": 1}, "yogeshojha.rengine/startScan/migrations/0019_auto_20201126_1457.py": {"loc": 18, "lloc": 4, "sloc": 12, "comments": 1, "multi": 0, "blank": 5, "single_comments": 1}, "yogeshojha.rengine/startScan/migrations/0020_waybackendpoint_discovered_date.py": {"loc": 18, "lloc": 4, "sloc": 12, "comments": 1, "multi": 0, "blank": 5, "single_comments": 1}, "yogeshojha.rengine/startScan/migrations/0021_auto_20201128_1916.py": {"loc": 18, "lloc": 4, "sloc": 12, "comments": 1, "multi": 0, "blank": 5, "single_comments": 1}, "yogeshojha.rengine/startScan/migrations/0022_auto_20201129_1058.py": {"loc": 18, "lloc": 4, "sloc": 12, "comments": 1, "multi": 0, "blank": 5, "single_comments": 1}, "yogeshojha.rengine/startScan/migrations/__init__.py": {"loc": 0, "lloc": 0, "sloc": 0, "comments": 0, "multi": 0, "blank": 0, "single_comments": 0}, "yogeshojha.rengine/startScan/templatetags/custom_tags.py": {"loc": 28, "lloc": 19, "sloc": 19, "comments": 0, "multi": 0, "blank": 9, "single_comments": 0}, "yogeshojha.rengine/startScan/templatetags/__init__.py": {"loc": 0, "lloc": 0, "sloc": 0, "comments": 0, "multi": 0, "blank": 0, "single_comments": 0}, "yogeshojha.rengine/targetApp/admin.py": {"loc": 4, "lloc": 3, "sloc": 3, "comments": 0, "multi": 0, "blank": 1, "single_comments": 0}, "yogeshojha.rengine/targetApp/apps.py": {"loc": 5, "lloc": 3, "sloc": 3, "comments": 0, "multi": 0, "blank": 2, "single_comments": 0}, "yogeshojha.rengine/targetApp/forms.py": {"loc": 52, "lloc": 19, "sloc": 47, "comments": 0, "multi": 0, "blank": 5, "single_comments": 0}, "yogeshojha.rengine/targetApp/models.py": {"loc": 12, "lloc": 9, "sloc": 9, "comments": 0, "multi": 0, "blank": 3, "single_comments": 0}, "yogeshojha.rengine/targetApp/tests.py": {"loc": 3, "lloc": 1, "sloc": 1, "comments": 1, "multi": 0, "blank": 1, "single_comments": 1}, "yogeshojha.rengine/targetApp/urls.py": {"loc": 35, "lloc": 4, "sloc": 33, "comments": 0, "multi": 0, "blank": 2, "single_comments": 0}, "yogeshojha.rengine/targetApp/views.py": {"loc": 164, "lloc": 106, "sloc": 148, "comments": 1, "multi": 0, "blank": 15, "single_comments": 1}, "yogeshojha.rengine/targetApp/__init__.py": {"loc": 0, "lloc": 0, "sloc": 0, "comments": 0, "multi": 0, "blank": 0, "single_comments": 0}, "yogeshojha.rengine/targetApp/migrations/0001_initial.py": {"loc": 24, "lloc": 5, "sloc": 17, "comments": 1, "multi": 0, "blank": 6, "single_comments": 1}, "yogeshojha.rengine/targetApp/migrations/0002_auto_20201128_1745.py": {"loc": 18, "lloc": 4, "sloc": 12, "comments": 1, "multi": 0, "blank": 5, "single_comments": 1}, "yogeshojha.rengine/targetApp/migrations/__init__.py": {"loc": 0, "lloc": 0, "sloc": 0, "comments": 0, "multi": 0, "blank": 0, "single_comments": 0}, "yogeshojha.rengine/tools/dirsearch/dirsearch.py": {"loc": 40, "lloc": 15, "sloc": 15, "comments": 18, "multi": 0, "blank": 7, "single_comments": 18}, "yogeshojha.rengine/tools/dirsearch/lib/__init__.py": {"loc": 1, "lloc": 1, "sloc": 1, "comments": 0, "multi": 0, "blank": 0, "single_comments": 0}, "yogeshojha.rengine/tools/dirsearch/lib/connection/Requester.py": {"loc": 213, "lloc": 115, "sloc": 145, "comments": 24, "multi": 0, "blank": 44, "single_comments": 24}, "yogeshojha.rengine/tools/dirsearch/lib/connection/RequestException.py": {"loc": 21, "lloc": 2, "sloc": 2, "comments": 17, "multi": 0, "blank": 2, "single_comments": 17}, "yogeshojha.rengine/tools/dirsearch/lib/connection/Response.py": {"loc": 64, "lloc": 35, "sloc": 35, "comments": 17, "multi": 0, "blank": 12, "single_comments": 17}, "yogeshojha.rengine/tools/dirsearch/lib/connection/__init__.py": {"loc": 3, "lloc": 3, "sloc": 3, "comments": 0, "multi": 0, "blank": 0, "single_comments": 0}, "yogeshojha.rengine/tools/dirsearch/lib/controller/Controller.py": {"loc": 486, "lloc": 321, "sloc": 349, "comments": 20, "multi": 2, "blank": 115, "single_comments": 20}, "yogeshojha.rengine/tools/dirsearch/lib/controller/__init__.py": {"loc": 1, "lloc": 1, "sloc": 1, "comments": 0, "multi": 0, "blank": 0, "single_comments": 0}, "yogeshojha.rengine/tools/dirsearch/lib/core/ArgumentParser.py": {"loc": 328, "lloc": 203, "sloc": 243, "comments": 25, "multi": 0, "blank": 60, "single_comments": 25}, "yogeshojha.rengine/tools/dirsearch/lib/core/Dictionary.py": {"loc": 158, "lloc": 87, "sloc": 85, "comments": 25, "multi": 14, "blank": 34, "single_comments": 25}, "yogeshojha.rengine/tools/dirsearch/lib/core/Fuzzer.py": {"loc": 176, "lloc": 118, "sloc": 119, "comments": 21, "multi": 0, "blank": 37, "single_comments": 20}, "yogeshojha.rengine/tools/dirsearch/lib/core/Path.py": {"loc": 27, "lloc": 7, "sloc": 7, "comments": 17, "multi": 0, "blank": 3, "single_comments": 17}, "yogeshojha.rengine/tools/dirsearch/lib/core/ReportManager.py": {"loc": 43, "lloc": 18, "sloc": 18, "comments": 17, "multi": 0, "blank": 8, "single_comments": 17}, "yogeshojha.rengine/tools/dirsearch/lib/core/Scanner.py": {"loc": 120, "lloc": 68, "sloc": 67, "comments": 24, "multi": 0, "blank": 30, "single_comments": 23}, "yogeshojha.rengine/tools/dirsearch/lib/core/__init__.py": {"loc": 5, "lloc": 5, "sloc": 5, "comments": 0, "multi": 0, "blank": 0, "single_comments": 0}, "yogeshojha.rengine/tools/dirsearch/lib/output/CLIOutput.py": {"loc": 204, "lloc": 141, "sloc": 141, "comments": 20, "multi": 0, "blank": 43, "single_comments": 20}, "yogeshojha.rengine/tools/dirsearch/lib/output/__init__.py": {"loc": 3, "lloc": 2, "sloc": 2, "comments": 0, "multi": 0, "blank": 1, "single_comments": 0}, "yogeshojha.rengine/tools/dirsearch/lib/reports/BaseReport.py": {"loc": 84, "lloc": 51, "sloc": 49, "comments": 17, "multi": 0, "blank": 18, "single_comments": 17}, "yogeshojha.rengine/tools/dirsearch/lib/reports/JSONReport.py": {"loc": 45, "lloc": 19, "sloc": 17, "comments": 17, "multi": 0, "blank": 11, "single_comments": 17}, "yogeshojha.rengine/tools/dirsearch/lib/reports/PlainTextReport.py": {"loc": 34, "lloc": 11, "sloc": 11, "comments": 17, "multi": 0, "blank": 6, "single_comments": 17}, "yogeshojha.rengine/tools/dirsearch/lib/reports/SimpleReport.py": {"loc": 30, "lloc": 8, "sloc": 8, "comments": 17, "multi": 0, "blank": 5, "single_comments": 17}, "yogeshojha.rengine/tools/dirsearch/lib/reports/__init__.py": {"loc": 6, "lloc": 5, "sloc": 5, "comments": 0, "multi": 0, "blank": 1, "single_comments": 0}, "yogeshojha.rengine/tools/dirsearch/lib/utils/DefaultConfigParser.py": {"loc": 64, "lloc": 40, "sloc": 40, "comments": 17, "multi": 0, "blank": 7, "single_comments": 17}, "yogeshojha.rengine/tools/dirsearch/lib/utils/FileUtils.py": {"loc": 146, "lloc": 101, "sloc": 101, "comments": 17, "multi": 0, "blank": 28, "single_comments": 17}, "yogeshojha.rengine/tools/dirsearch/lib/utils/RandomUtils.py": {"loc": 29, "lloc": 9, "sloc": 9, "comments": 17, "multi": 0, "blank": 3, "single_comments": 17}, "yogeshojha.rengine/tools/dirsearch/lib/utils/TerminalSize.py": {"loc": 105, "lloc": 64, "sloc": 66, "comments": 24, "multi": 6, "blank": 10, "single_comments": 23}, "yogeshojha.rengine/tools/dirsearch/lib/utils/__init__.py": {"loc": 4, "lloc": 4, "sloc": 4, "comments": 0, "multi": 0, "blank": 0, "single_comments": 0}, "yogeshojha.rengine/tools/dirsearch/thirdparty/__init__.py": {"loc": 3, "lloc": 1, "sloc": 1, "comments": 1, "multi": 0, "blank": 1, "single_comments": 1}, "yogeshojha.rengine/tools/dirsearch/thirdparty/chardet/gb2312freq.py": {"loc": 283, "lloc": 3, "sloc": 239, "comments": 39, "multi": 0, "blank": 6, "single_comments": 38}, "yogeshojha.rengine/tools/dirsearch/thirdparty/chardet/big5freq.py": {"loc": 386, "lloc": 3, "sloc": 340, "comments": 377, "multi": 0, "blank": 5, "single_comments": 41}, "yogeshojha.rengine/tools/dirsearch/thirdparty/chardet/big5prober.py": {"loc": 47, "lloc": 16, "sloc": 16, "comments": 26, "multi": 0, "blank": 5, "single_comments": 26}, "yogeshojha.rengine/tools/dirsearch/thirdparty/chardet/chardistribution.py": {"loc": 233, "lloc": 128, "sloc": 131, "comments": 72, "multi": 0, "blank": 29, "single_comments": 73}, "yogeshojha.rengine/tools/dirsearch/thirdparty/chardet/charsetgroupprober.py": {"loc": 106, "lloc": 72, "sloc": 72, "comments": 26, "multi": 0, "blank": 8, "single_comments": 26}, "yogeshojha.rengine/tools/dirsearch/thirdparty/chardet/charsetprober.py": {"loc": 145, "lloc": 62, "sloc": 56, "comments": 44, "multi": 20, "blank": 25, "single_comments": 44}, "yogeshojha.rengine/tools/dirsearch/thirdparty/chardet/codingstatemachine.py": {"loc": 88, "lloc": 29, "sloc": 29, "comments": 29, "multi": 18, "blank": 12, "single_comments": 29}, "yogeshojha.rengine/tools/dirsearch/thirdparty/chardet/compat.py": {"loc": 34, "lloc": 11, "sloc": 11, "comments": 20, "multi": 0, "blank": 3, "single_comments": 20}, "yogeshojha.rengine/tools/dirsearch/thirdparty/chardet/cp949prober.py": {"loc": 49, "lloc": 16, "sloc": 16, "comments": 28, "multi": 0, "blank": 5, "single_comments": 28}, "yogeshojha.rengine/tools/dirsearch/thirdparty/chardet/enums.py": {"loc": 76, "lloc": 43, "sloc": 35, "comments": 0, "multi": 25, "blank": 15, "single_comments": 1}, "yogeshojha.rengine/tools/dirsearch/thirdparty/chardet/escprober.py": {"loc": 101, "lloc": 60, "sloc": 60, "comments": 26, "multi": 5, "blank": 10, "single_comments": 26}, "yogeshojha.rengine/tools/dirsearch/thirdparty/chardet/escsm.py": {"loc": 246, "lloc": 21, "sloc": 201, "comments": 182, "multi": 0, "blank": 19, "single_comments": 26}, "yogeshojha.rengine/tools/dirsearch/thirdparty/chardet/eucjpprober.py": {"loc": 92, "lloc": 52, "sloc": 54, "comments": 27, "multi": 0, "blank": 11, "single_comments": 27}, "yogeshojha.rengine/tools/dirsearch/thirdparty/chardet/euckrfreq.py": {"loc": 195, "lloc": 3, "sloc": 151, "comments": 39, "multi": 0, "blank": 6, "single_comments": 38}, "yogeshojha.rengine/tools/dirsearch/thirdparty/chardet/euckrprober.py": {"loc": 47, "lloc": 16, "sloc": 16, "comments": 26, "multi": 0, "blank": 5, "single_comments": 26}, "yogeshojha.rengine/tools/dirsearch/thirdparty/chardet/euctwfreq.py": {"loc": 387, "lloc": 3, "sloc": 340, "comments": 377, "multi": 0, "blank": 6, "single_comments": 41}, "yogeshojha.rengine/tools/dirsearch/thirdparty/chardet/euctwprober.py": {"loc": 46, "lloc": 16, "sloc": 16, "comments": 26, "multi": 0, "blank": 4, "single_comments": 26}, "yogeshojha.rengine/tools/dirsearch/thirdparty/chardet/gb2312prober.py": {"loc": 46, "lloc": 16, "sloc": 16, "comments": 26, "multi": 0, "blank": 4, "single_comments": 26}, "yogeshojha.rengine/tools/dirsearch/thirdparty/chardet/hebrewprober.py": {"loc": 292, "lloc": 78, "sloc": 83, "comments": 186, "multi": 0, "blank": 23, "single_comments": 186}, "yogeshojha.rengine/tools/dirsearch/thirdparty/chardet/jisfreq.py": {"loc": 325, "lloc": 3, "sloc": 277, "comments": 314, "multi": 0, "blank": 7, "single_comments": 41}, "yogeshojha.rengine/tools/dirsearch/thirdparty/chardet/jpcntx.py": {"loc": 233, "lloc": 86, "sloc": 169, "comments": 46, "multi": 0, "blank": 20, "single_comments": 44}, "yogeshojha.rengine/tools/dirsearch/thirdparty/chardet/langbulgarianmodel.py": {"loc": 228, "lloc": 7, "sloc": 182, "comments": 71, "multi": 0, "blank": 7, "single_comments": 39}, "yogeshojha.rengine/tools/dirsearch/thirdparty/chardet/langcyrillicmodel.py": {"loc": 333, "lloc": 19, "sloc": 286, "comments": 90, "multi": 0, "blank": 13, "single_comments": 34}, "yogeshojha.rengine/tools/dirsearch/thirdparty/chardet/langgreekmodel.py": {"loc": 225, "lloc": 7, "sloc": 182, "comments": 69, "multi": 0, "blank": 6, "single_comments": 37}, "yogeshojha.rengine/tools/dirsearch/thirdparty/chardet/langhebrewmodel.py": {"loc": 200, "lloc": 4, "sloc": 156, "comments": 48, "multi": 0, "blank": 4, "single_comments": 40}, "yogeshojha.rengine/tools/dirsearch/thirdparty/chardet/langhungarianmodel.py": {"loc": 225, "lloc": 7, "sloc": 182, "comments": 45, "multi": 0, "blank": 6, "single_comments": 37}, "yogeshojha.rengine/tools/dirsearch/thirdparty/chardet/langthaimodel.py": {"loc": 199, "lloc": 4, "sloc": 156, "comments": 46, "multi": 0, "blank": 5, "single_comments": 38}, "yogeshojha.rengine/tools/dirsearch/thirdparty/chardet/langturkishmodel.py": {"loc": 193, "lloc": 4, "sloc": 156, "comments": 33, "multi": 0, "blank": 4, "single_comments": 33}, "yogeshojha.rengine/tools/dirsearch/thirdparty/chardet/latin1prober.py": {"loc": 145, "lloc": 53, "sloc": 98, "comments": 83, "multi": 0, "blank": 14, "single_comments": 33}, "yogeshojha.rengine/tools/dirsearch/thirdparty/chardet/mbcharsetprober.py": {"loc": 91, "lloc": 47, "sloc": 48, "comments": 28, "multi": 3, "blank": 12, "single_comments": 28}, "yogeshojha.rengine/tools/dirsearch/thirdparty/chardet/mbcsgroupprober.py": {"loc": 54, "lloc": 14, "sloc": 23, "comments": 28, "multi": 0, "blank": 3, "single_comments": 28}, "yogeshojha.rengine/tools/dirsearch/thirdparty/chardet/mbcssm.py": {"loc": 572, "lloc": 51, "sloc": 479, "comments": 420, "multi": 0, "blank": 52, "single_comments": 41}, "yogeshojha.rengine/tools/dirsearch/thirdparty/chardet/sbcharsetprober.py": {"loc": 132, "lloc": 78, "sloc": 83, "comments": 40, "multi": 0, "blank": 11, "single_comments": 38}, "yogeshojha.rengine/tools/dirsearch/thirdparty/chardet/sbcsgroupprober.py": {"loc": 73, "lloc": 19, "sloc": 41, "comments": 32, "multi": 0, "blank": 4, "single_comments": 28}, "yogeshojha.rengine/tools/dirsearch/thirdparty/chardet/sjisprober.py": {"loc": 92, "lloc": 53, "sloc": 55, "comments": 26, "multi": 0, "blank": 11, "single_comments": 26}, "yogeshojha.rengine/tools/dirsearch/thirdparty/chardet/universaldetector.py": {"loc": 286, "lloc": 141, "sloc": 161, "comments": 55, "multi": 41, "blank": 29, "single_comments": 55}, "yogeshojha.rengine/tools/dirsearch/thirdparty/chardet/utf8prober.py": {"loc": 82, "lloc": 44, "sloc": 44, "comments": 26, "multi": 0, "blank": 12, "single_comments": 26}, "yogeshojha.rengine/tools/dirsearch/thirdparty/chardet/version.py": {"loc": 9, "lloc": 3, "sloc": 2, "comments": 0, "multi": 5, "blank": 2, "single_comments": 0}, "yogeshojha.rengine/tools/dirsearch/thirdparty/chardet/__init__.py": {"loc": 39, "lloc": 13, "sloc": 13, "comments": 16, "multi": 5, "blank": 5, "single_comments": 16}, "yogeshojha.rengine/tools/dirsearch/thirdparty/chardet/cli/chardetect.py": {"loc": 85, "lloc": 35, "sloc": 43, "comments": 3, "multi": 23, "blank": 16, "single_comments": 3}, "yogeshojha.rengine/tools/dirsearch/thirdparty/chardet/cli/__init__.py": {"loc": 1, "lloc": 0, "sloc": 0, "comments": 0, "multi": 0, "blank": 1, "single_comments": 0}, "yogeshojha.rengine/tools/dirsearch/thirdparty/colorama/ansi.py": {"loc": 102, "lloc": 74, "sloc": 73, "comments": 6, "multi": 4, "blank": 19, "single_comments": 6}, "yogeshojha.rengine/tools/dirsearch/thirdparty/colorama/ansitowin32.py": {"loc": 232, "lloc": 123, "sloc": 153, "comments": 25, "multi": 22, "blank": 37, "single_comments": 20}, "yogeshojha.rengine/tools/dirsearch/thirdparty/colorama/initialise.py": {"loc": 81, "lloc": 53, "sloc": 56, "comments": 1, "multi": 0, "blank": 24, "single_comments": 1}, "yogeshojha.rengine/tools/dirsearch/thirdparty/colorama/win32.py": {"loc": 154, "lloc": 84, "sloc": 123, "comments": 10, "multi": 0, "blank": 19, "single_comments": 12}, "yogeshojha.rengine/tools/dirsearch/thirdparty/colorama/winterm.py": {"loc": 162, "lloc": 118, "sloc": 118, "comments": 29, "multi": 0, "blank": 18, "single_comments": 26}, "yogeshojha.rengine/tools/dirsearch/thirdparty/colorama/__init__.py": {"loc": 7, "lloc": 4, "sloc": 4, "comments": 1, "multi": 0, "blank": 2, "single_comments": 1}, "yogeshojha.rengine/tools/dirsearch/thirdparty/oset/pyoset.py": {"loc": 82, "lloc": 58, "sloc": 57, "comments": 6, "multi": 0, "blank": 21, "single_comments": 4}, "yogeshojha.rengine/tools/dirsearch/thirdparty/oset/tests.py": {"loc": 44, "lloc": 21, "sloc": 29, "comments": 2, "multi": 0, "blank": 11, "single_comments": 4}, "yogeshojha.rengine/tools/dirsearch/thirdparty/oset/_abc.py": {"loc": 469, "lloc": 312, "sloc": 303, "comments": 29, "multi": 46, "blank": 86, "single_comments": 34}, "yogeshojha.rengine/tools/dirsearch/thirdparty/oset/__init__.py": {"loc": 3, "lloc": 2, "sloc": 1, "comments": 0, "multi": 0, "blank": 1, "single_comments": 1}, "yogeshojha.rengine/tools/dirsearch/thirdparty/requests/adapters.py": {"loc": 432, "lloc": 197, "sloc": 220, "comments": 15, "multi": 107, "blank": 89, "single_comments": 16}, "yogeshojha.rengine/tools/dirsearch/thirdparty/requests/api.py": {"loc": 147, "lloc": 32, "sloc": 23, "comments": 4, "multi": 81, "blank": 39, "single_comments": 4}, "yogeshojha.rengine/tools/dirsearch/thirdparty/requests/auth.py": {"loc": 212, "lloc": 145, "sloc": 141, "comments": 15, "multi": 5, "blank": 44, "single_comments": 22}, "yogeshojha.rengine/tools/dirsearch/thirdparty/requests/certs.py": {"loc": 25, "lloc": 10, "sloc": 8, "comments": 3, "multi": 8, "blank": 5, "single_comments": 4}, "yogeshojha.rengine/tools/dirsearch/thirdparty/requests/compat.py": {"loc": 62, "lloc": 35, "sloc": 34, "comments": 12, "multi": 3, "blank": 13, "single_comments": 12}, "yogeshojha.rengine/tools/dirsearch/thirdparty/requests/cookies.py": {"loc": 482, "lloc": 268, "sloc": 265, "comments": 15, "multi": 100, "blank": 96, "single_comments": 21}, "yogeshojha.rengine/tools/dirsearch/thirdparty/requests/exceptions.py": {"loc": 99, "lloc": 44, "sloc": 26, "comments": 1, "multi": 18, "blank": 40, "single_comments": 15}, "yogeshojha.rengine/tools/dirsearch/thirdparty/requests/hooks.py": {"loc": 34, "lloc": 16, "sloc": 14, "comments": 2, "multi": 8, "blank": 9, "single_comments": 3}, "yogeshojha.rengine/tools/dirsearch/thirdparty/requests/models.py": {"loc": 848, "lloc": 464, "sloc": 475, "comments": 95, "multi": 90, "blank": 175, "single_comments": 108}, "yogeshojha.rengine/tools/dirsearch/thirdparty/requests/sessions.py": {"loc": 682, "lloc": 281, "sloc": 324, "comments": 81, "multi": 116, "blank": 157, "single_comments": 85}, "yogeshojha.rengine/tools/dirsearch/thirdparty/requests/status_codes.py": {"loc": 89, "lloc": 9, "sloc": 80, "comments": 6, "multi": 0, "blank": 8, "single_comments": 1}, "yogeshojha.rengine/tools/dirsearch/thirdparty/requests/structures.py": {"loc": 104, "lloc": 43, "sloc": 43, "comments": 6, "multi": 26, "blank": 27, "single_comments": 8}, "yogeshojha.rengine/tools/dirsearch/thirdparty/requests/utils.py": {"loc": 720, "lloc": 384, "sloc": 369, "comments": 62, "multi": 119, "blank": 170, "single_comments": 62}, "yogeshojha.rengine/tools/dirsearch/thirdparty/requests/__init__.py": {"loc": 77, "lloc": 26, "sloc": 28, "comments": 8, "multi": 28, "blank": 14, "single_comments": 7}, "yogeshojha.rengine/tools/dirsearch/thirdparty/requests/packages/__init__.py": {"loc": 3, "lloc": 2, "sloc": 2, "comments": 0, "multi": 0, "blank": 1, "single_comments": 0}, "yogeshojha.rengine/tools/dirsearch/thirdparty/requests/packages/chardet/gb2312freq.py": {"loc": 472, "lloc": 3, "sloc": 427, "comments": 41, "multi": 0, "blank": 6, "single_comments": 39}, "yogeshojha.rengine/tools/dirsearch/thirdparty/requests/packages/chardet/big5freq.py": {"loc": 925, "lloc": 3, "sloc": 878, "comments": 917, "multi": 0, "blank": 5, "single_comments": 42}, "yogeshojha.rengine/tools/dirsearch/thirdparty/requests/packages/chardet/big5prober.py": {"loc": 42, "lloc": 12, "sloc": 12, "comments": 26, "multi": 0, "blank": 4, "single_comments": 26}, "yogeshojha.rengine/tools/dirsearch/thirdparty/requests/packages/chardet/chardetect.py": {"loc": 80, "lloc": 30, "sloc": 39, "comments": 2, "multi": 23, "blank": 16, "single_comments": 2}, "yogeshojha.rengine/tools/dirsearch/thirdparty/requests/packages/chardet/chardistribution.py": {"loc": 231, "lloc": 126, "sloc": 129, "comments": 72, "multi": 0, "blank": 29, "single_comments": 73}, "yogeshojha.rengine/tools/dirsearch/thirdparty/requests/packages/chardet/charsetgroupprober.py": {"loc": 106, "lloc": 67, "sloc": 69, "comments": 30, "multi": 0, "blank": 7, "single_comments": 30}, "yogeshojha.rengine/tools/dirsearch/thirdparty/requests/packages/chardet/charsetprober.py": {"loc": 62, "lloc": 23, "sloc": 23, "comments": 28, "multi": 0, "blank": 11, "single_comments": 28}, "yogeshojha.rengine/tools/dirsearch/thirdparty/requests/packages/chardet/codingstatemachine.py": {"loc": 61, "lloc": 23, "sloc": 24, "comments": 30, "multi": 0, "blank": 7, "single_comments": 30}, "yogeshojha.rengine/tools/dirsearch/thirdparty/requests/packages/chardet/compat.py": {"loc": 34, "lloc": 10, "sloc": 10, "comments": 19, "multi": 0, "blank": 5, "single_comments": 19}, "yogeshojha.rengine/tools/dirsearch/thirdparty/requests/packages/chardet/constants.py": {"loc": 39, "lloc": 8, "sloc": 8, "comments": 27, "multi": 0, "blank": 4, "single_comments": 27}, "yogeshojha.rengine/tools/dirsearch/thirdparty/requests/packages/chardet/cp949prober.py": {"loc": 44, "lloc": 12, "sloc": 12, "comments": 28, "multi": 0, "blank": 4, "single_comments": 28}, "yogeshojha.rengine/tools/dirsearch/thirdparty/requests/packages/chardet/escprober.py": {"loc": 86, "lloc": 45, "sloc": 51, "comments": 28, "multi": 0, "blank": 8, "single_comments": 27}, "yogeshojha.rengine/tools/dirsearch/thirdparty/requests/packages/chardet/escsm.py": {"loc": 242, "lloc": 21, "sloc": 197, "comments": 183, "multi": 0, "blank": 18, "single_comments": 27}, "yogeshojha.rengine/tools/dirsearch/thirdparty/requests/packages/chardet/eucjpprober.py": {"loc": 90, "lloc": 51, "sloc": 53, "comments": 27, "multi": 0, "blank": 10, "single_comments": 27}, "yogeshojha.rengine/tools/dirsearch/thirdparty/requests/packages/chardet/euckrfreq.py": {"loc": 596, "lloc": 3, "sloc": 551, "comments": 42, "multi": 0, "blank": 6, "single_comments": 39}, "yogeshojha.rengine/tools/dirsearch/thirdparty/requests/packages/chardet/euckrprober.py": {"loc": 42, "lloc": 12, "sloc": 12, "comments": 26, "multi": 0, "blank": 4, "single_comments": 26}, "yogeshojha.rengine/tools/dirsearch/thirdparty/requests/packages/chardet/euctwfreq.py": {"loc": 428, "lloc": 3, "sloc": 380, "comments": 419, "multi": 0, "blank": 6, "single_comments": 42}, "yogeshojha.rengine/tools/dirsearch/thirdparty/requests/packages/chardet/euctwprober.py": {"loc": 41, "lloc": 12, "sloc": 12, "comments": 26, "multi": 0, "blank": 3, "single_comments": 26}, "yogeshojha.rengine/tools/dirsearch/thirdparty/requests/packages/chardet/gb2312prober.py": {"loc": 41, "lloc": 12, "sloc": 12, "comments": 26, "multi": 0, "blank": 3, "single_comments": 26}, "yogeshojha.rengine/tools/dirsearch/thirdparty/requests/packages/chardet/hebrewprober.py": {"loc": 283, "lloc": 70, "sloc": 74, "comments": 186, "multi": 0, "blank": 23, "single_comments": 186}, "yogeshojha.rengine/tools/dirsearch/thirdparty/requests/packages/chardet/jisfreq.py": {"loc": 569, "lloc": 3, "sloc": 521, "comments": 560, "multi": 0, "blank": 6, "single_comments": 42}, "yogeshojha.rengine/tools/dirsearch/thirdparty/requests/packages/chardet/jpcntx.py": {"loc": 227, "lloc": 80, "sloc": 163, "comments": 47, "multi": 0, "blank": 19, "single_comments": 45}, "yogeshojha.rengine/tools/dirsearch/thirdparty/requests/packages/chardet/langbulgarianmodel.py": {"loc": 229, "lloc": 7, "sloc": 180, "comments": 72, "multi": 0, "blank": 9, "single_comments": 40}, "yogeshojha.rengine/tools/dirsearch/thirdparty/requests/packages/chardet/langcyrillicmodel.py": {"loc": 329, "lloc": 19, "sloc": 280, "comments": 91, "multi": 0, "blank": 14, "single_comments": 35}, "yogeshojha.rengine/tools/dirsearch/thirdparty/requests/packages/chardet/langgreekmodel.py": {"loc": 225, "lloc": 7, "sloc": 180, "comments": 70, "multi": 0, "blank": 7, "single_comments": 38}, "yogeshojha.rengine/tools/dirsearch/thirdparty/requests/packages/chardet/langhebrewmodel.py": {"loc": 201, "lloc": 4, "sloc": 155, "comments": 49, "multi": 0, "blank": 5, "single_comments": 41}, "yogeshojha.rengine/tools/dirsearch/thirdparty/requests/packages/chardet/langhungarianmodel.py": {"loc": 225, "lloc": 7, "sloc": 180, "comments": 46, "multi": 0, "blank": 7, "single_comments": 38}, "yogeshojha.rengine/tools/dirsearch/thirdparty/requests/packages/chardet/langthaimodel.py": {"loc": 200, "lloc": 4, "sloc": 155, "comments": 47, "multi": 0, "blank": 6, "single_comments": 39}, "yogeshojha.rengine/tools/dirsearch/thirdparty/requests/packages/chardet/latin1prober.py": {"loc": 139, "lloc": 48, "sloc": 93, "comments": 83, "multi": 0, "blank": 13, "single_comments": 33}, "yogeshojha.rengine/tools/dirsearch/thirdparty/requests/packages/chardet/mbcharsetprober.py": {"loc": 86, "lloc": 45, "sloc": 48, "comments": 28, "multi": 0, "blank": 10, "single_comments": 28}, "yogeshojha.rengine/tools/dirsearch/thirdparty/requests/packages/chardet/mbcsgroupprober.py": {"loc": 54, "lloc": 14, "sloc": 23, "comments": 28, "multi": 0, "blank": 3, "single_comments": 28}, "yogeshojha.rengine/tools/dirsearch/thirdparty/requests/packages/chardet/mbcssm.py": {"loc": 572, "lloc": 51, "sloc": 479, "comments": 420, "multi": 0, "blank": 52, "single_comments": 41}, "yogeshojha.rengine/tools/dirsearch/thirdparty/requests/packages/chardet/sbcharsetprober.py": {"loc": 120, "lloc": 72, "sloc": 78, "comments": 33, "multi": 0, "blank": 10, "single_comments": 32}, "yogeshojha.rengine/tools/dirsearch/thirdparty/requests/packages/chardet/sbcsgroupprober.py": {"loc": 69, "lloc": 19, "sloc": 38, "comments": 27, "multi": 0, "blank": 4, "single_comments": 27}, "yogeshojha.rengine/tools/dirsearch/thirdparty/requests/packages/chardet/sjisprober.py": {"loc": 91, "lloc": 52, "sloc": 55, "comments": 26, "multi": 0, "blank": 10, "single_comments": 26}, "yogeshojha.rengine/tools/dirsearch/thirdparty/requests/packages/chardet/universaldetector.py": {"loc": 170, "lloc": 119, "sloc": 119, "comments": 39, "multi": 0, "blank": 16, "single_comments": 35}, "yogeshojha.rengine/tools/dirsearch/thirdparty/requests/packages/chardet/utf8prober.py": {"loc": 76, "lloc": 40, "sloc": 40, "comments": 26, "multi": 0, "blank": 10, "single_comments": 26}, "yogeshojha.rengine/tools/dirsearch/thirdparty/requests/packages/chardet/__init__.py": {"loc": 32, "lloc": 11, "sloc": 12, "comments": 16, "multi": 0, "blank": 4, "single_comments": 16}, "yogeshojha.rengine/tools/dirsearch/thirdparty/requests/packages/urllib3/connection.py": {"loc": 264, "lloc": 117, "sloc": 147, "comments": 36, "multi": 25, "blank": 62, "single_comments": 30}, "yogeshojha.rengine/tools/dirsearch/thirdparty/requests/packages/urllib3/connectionpool.py": {"loc": 796, "lloc": 304, "sloc": 356, "comments": 92, "multi": 201, "blank": 158, "single_comments": 81}, "yogeshojha.rengine/tools/dirsearch/thirdparty/requests/packages/urllib3/exceptions.py": {"loc": 169, "lloc": 91, "sloc": 68, "comments": 7, "multi": 10, "blank": 62, "single_comments": 29}, "yogeshojha.rengine/tools/dirsearch/thirdparty/requests/packages/urllib3/fields.py": {"loc": 177, "lloc": 80, "sloc": 77, "comments": 1, "multi": 68, "blank": 32, "single_comments": 0}, "yogeshojha.rengine/tools/dirsearch/thirdparty/requests/packages/urllib3/filepost.py": {"loc": 93, "lloc": 45, "sloc": 41, "comments": 1, "multi": 24, "blank": 28, "single_comments": 0}, "yogeshojha.rengine/tools/dirsearch/thirdparty/requests/packages/urllib3/poolmanager.py": {"loc": 280, "lloc": 129, "sloc": 128, "comments": 10, "multi": 75, "blank": 67, "single_comments": 10}, "yogeshojha.rengine/tools/dirsearch/thirdparty/requests/packages/urllib3/request.py": {"loc": 141, "lloc": 44, "sloc": 47, "comments": 1, "multi": 62, "blank": 32, "single_comments": 0}, "yogeshojha.rengine/tools/dirsearch/thirdparty/requests/packages/urllib3/response.py": {"loc": 466, "lloc": 264, "sloc": 270, "comments": 43, "multi": 79, "blank": 83, "single_comments": 34}, "yogeshojha.rengine/tools/dirsearch/thirdparty/requests/packages/urllib3/_collections.py": {"loc": 323, "lloc": 197, "sloc": 186, "comments": 22, "multi": 52, "blank": 64, "single_comments": 21}, "yogeshojha.rengine/tools/dirsearch/thirdparty/requests/packages/urllib3/__init__.py": {"loc": 69, "lloc": 37, "sloc": 39, "comments": 7, "multi": 11, "blank": 13, "single_comments": 6}, "yogeshojha.rengine/tools/dirsearch/thirdparty/requests/packages/urllib3/contrib/ntlmpool.py": {"loc": 114, "lloc": 68, "sloc": 77, "comments": 7, "multi": 12, "blank": 18, "single_comments": 7}, "yogeshojha.rengine/tools/dirsearch/thirdparty/requests/packages/urllib3/contrib/pyopenssl.py": {"loc": 293, "lloc": 165, "sloc": 179, "comments": 12, "multi": 36, "blank": 64, "single_comments": 14}, "yogeshojha.rengine/tools/dirsearch/thirdparty/requests/packages/urllib3/contrib/__init__.py": {"loc": 0, "lloc": 0, "sloc": 0, "comments": 0, "multi": 0, "blank": 0, "single_comments": 0}, "yogeshojha.rengine/tools/dirsearch/thirdparty/requests/packages/urllib3/packages/ordered_dict.py": {"loc": 259, "lloc": 186, "sloc": 159, "comments": 21, "multi": 22, "blank": 40, "single_comments": 38}, "yogeshojha.rengine/tools/dirsearch/thirdparty/requests/packages/urllib3/packages/six.py": {"loc": 385, "lloc": 241, "sloc": 276, "comments": 23, "multi": 0, "blank": 75, "single_comments": 34}, "yogeshojha.rengine/tools/dirsearch/thirdparty/requests/packages/urllib3/packages/__init__.py": {"loc": 4, "lloc": 2, "sloc": 2, "comments": 0, "multi": 0, "blank": 2, "single_comments": 0}, "yogeshojha.rengine/tools/dirsearch/thirdparty/requests/packages/urllib3/packages/ssl_match_hostname/_implementation.py": {"loc": 105, "lloc": 53, "sloc": 55, "comments": 24, "multi": 9, "blank": 16, "single_comments": 25}, "yogeshojha.rengine/tools/dirsearch/thirdparty/requests/packages/urllib3/packages/ssl_match_hostname/__init__.py": {"loc": 13, "lloc": 8, "sloc": 8, "comments": 4, "multi": 0, "blank": 1, "single_comments": 4}, "yogeshojha.rengine/tools/dirsearch/thirdparty/requests/packages/urllib3/util/connection.py": {"loc": 98, "lloc": 58, "sloc": 57, "comments": 12, "multi": 17, "blank": 18, "single_comments": 6}, "yogeshojha.rengine/tools/dirsearch/thirdparty/requests/packages/urllib3/util/request.py": {"loc": 71, "lloc": 25, "sloc": 27, "comments": 0, "multi": 26, "blank": 18, "single_comments": 0}, "yogeshojha.rengine/tools/dirsearch/thirdparty/requests/packages/urllib3/util/response.py": {"loc": 22, "lloc": 11, "sloc": 10, "comments": 3, "multi": 5, "blank": 4, "single_comments": 3}, "yogeshojha.rengine/tools/dirsearch/thirdparty/requests/packages/urllib3/util/retry.py": {"loc": 285, "lloc": 108, "sloc": 122, "comments": 9, "multi": 79, "blank": 74, "single_comments": 10}, "yogeshojha.rengine/tools/dirsearch/thirdparty/requests/packages/urllib3/util/ssl_.py": {"loc": 280, "lloc": 120, "sloc": 145, "comments": 37, "multi": 59, "blank": 50, "single_comments": 26}, "yogeshojha.rengine/tools/dirsearch/thirdparty/requests/packages/urllib3/util/timeout.py": {"loc": 240, "lloc": 71, "sloc": 73, "comments": 10, "multi": 106, "blank": 52, "single_comments": 9}, "yogeshojha.rengine/tools/dirsearch/thirdparty/requests/packages/urllib3/util/url.py": {"loc": 214, "lloc": 108, "sloc": 101, "comments": 18, "multi": 44, "blank": 48, "single_comments": 21}, "yogeshojha.rengine/tools/dirsearch/thirdparty/requests/packages/urllib3/util/__init__.py": {"loc": 24, "lloc": 7, "sloc": 22, "comments": 1, "multi": 0, "blank": 1, "single_comments": 1}, "yogeshojha.rengine/tools/dirsearch/thirdparty/sqlmap/DynamicContentParser.py": {"loc": 106, "lloc": 81, "sloc": 78, "comments": 4, "multi": 4, "blank": 20, "single_comments": 4}, "yogeshojha.rengine/tools/dirsearch/thirdparty/sqlmap/__init__.py": {"loc": 1, "lloc": 1, "sloc": 1, "comments": 0, "multi": 0, "blank": 0, "single_comments": 0}, "yogeshojha.rengine/tools/OneForAll/brute.py": {"loc": 510, "lloc": 385, "sloc": 394, "comments": 29, "multi": 54, "blank": 50, "single_comments": 12}, "yogeshojha.rengine/tools/OneForAll/export.py": {"loc": 70, "lloc": 34, "sloc": 32, "comments": 2, "multi": 22, "blank": 14, "single_comments": 2}, "yogeshojha.rengine/tools/OneForAll/oneforall.py": {"loc": 273, "lloc": 153, "sloc": 153, "comments": 19, "multi": 63, "blank": 42, "single_comments": 15}, "yogeshojha.rengine/tools/OneForAll/takeover.py": {"loc": 168, "lloc": 119, "sloc": 120, "comments": 9, "multi": 19, "blank": 24, "single_comments": 5}, "yogeshojha.rengine/tools/OneForAll/common/check.py": {"loc": 41, "lloc": 28, "sloc": 33, "comments": 0, "multi": 3, "blank": 5, "single_comments": 0}, "yogeshojha.rengine/tools/OneForAll/common/crawl.py": {"loc": 10, "lloc": 5, "sloc": 4, "comments": 0, "multi": 3, "blank": 3, "single_comments": 0}, "yogeshojha.rengine/tools/OneForAll/common/database.py": {"loc": 277, "lloc": 134, "sloc": 180, "comments": 2, "multi": 62, "blank": 35, "single_comments": 0}, "yogeshojha.rengine/tools/OneForAll/common/domain.py": {"loc": 61, "lloc": 30, "sloc": 26, "comments": 0, "multi": 24, "blank": 11, "single_comments": 0}, "yogeshojha.rengine/tools/OneForAll/common/ipasn.py": {"loc": 42, "lloc": 35, "sloc": 34, "comments": 0, "multi": 0, "blank": 8, "single_comments": 0}, "yogeshojha.rengine/tools/OneForAll/common/ipreg.py": {"loc": 139, "lloc": 105, "sloc": 99, "comments": 1, "multi": 18, "blank": 22, "single_comments": 0}, "yogeshojha.rengine/tools/OneForAll/common/lookup.py": {"loc": 28, "lloc": 19, "sloc": 17, "comments": 0, "multi": 7, "blank": 4, "single_comments": 0}, "yogeshojha.rengine/tools/OneForAll/common/module.py": {"loc": 369, "lloc": 192, "sloc": 276, "comments": 11, "multi": 66, "blank": 27, "single_comments": 0}, "yogeshojha.rengine/tools/OneForAll/common/query.py": {"loc": 9, "lloc": 5, "sloc": 4, "comments": 0, "multi": 3, "blank": 2, "single_comments": 0}, "yogeshojha.rengine/tools/OneForAll/common/records.py": {"loc": 363, "lloc": 230, "sloc": 206, "comments": 26, "multi": 27, "blank": 88, "single_comments": 42}, "yogeshojha.rengine/tools/OneForAll/common/request.py": {"loc": 264, "lloc": 207, "sloc": 206, "comments": 3, "multi": 12, "blank": 44, "single_comments": 2}, "yogeshojha.rengine/tools/OneForAll/common/resolve.py": {"loc": 172, "lloc": 130, "sloc": 125, "comments": 3, "multi": 23, "blank": 24, "single_comments": 0}, "yogeshojha.rengine/tools/OneForAll/common/search.py": {"loc": 77, "lloc": 44, "sloc": 39, "comments": 8, "multi": 24, "blank": 9, "single_comments": 5}, "yogeshojha.rengine/tools/OneForAll/common/similarity.py": {"loc": 138, "lloc": 97, "sloc": 97, "comments": 0, "multi": 20, "blank": 21, "single_comments": 0}, "yogeshojha.rengine/tools/OneForAll/common/tldextract.py": {"loc": 240, "lloc": 104, "sloc": 95, "comments": 5, "multi": 84, "blank": 55, "single_comments": 6}, "yogeshojha.rengine/tools/OneForAll/common/utils.py": {"loc": 780, "lloc": 552, "sloc": 553, "comments": 11, "multi": 84, "blank": 136, "single_comments": 7}, "yogeshojha.rengine/tools/OneForAll/common/tablib/format.py": {"loc": 89, "lloc": 54, "sloc": 48, "comments": 4, "multi": 7, "blank": 27, "single_comments": 7}, "yogeshojha.rengine/tools/OneForAll/common/tablib/tablib.py": {"loc": 360, "lloc": 189, "sloc": 169, "comments": 12, "multi": 72, "blank": 98, "single_comments": 21}, "yogeshojha.rengine/tools/OneForAll/common/tablib/__init__.py": {"loc": 0, "lloc": 0, "sloc": 0, "comments": 0, "multi": 0, "blank": 0, "single_comments": 0}, "yogeshojha.rengine/tools/OneForAll/config/api.py": {"loc": 76, "lloc": 28, "sloc": 28, "comments": 35, "multi": 0, "blank": 17, "single_comments": 31}, "yogeshojha.rengine/tools/OneForAll/config/default.py": {"loc": 239, "lloc": 105, "sloc": 140, "comments": 133, "multi": 3, "blank": 33, "single_comments": 63}, "yogeshojha.rengine/tools/OneForAll/config/log.py": {"loc": 38, "lloc": 18, "sloc": 26, "comments": 10, "multi": 0, "blank": 5, "single_comments": 7}, "yogeshojha.rengine/tools/OneForAll/config/setting.py": {"loc": 77, "lloc": 44, "sloc": 46, "comments": 58, "multi": 3, "blank": 7, "single_comments": 21}, "yogeshojha.rengine/tools/OneForAll/config/__init__.py": {"loc": 17, "lloc": 12, "sloc": 12, "comments": 1, "multi": 0, "blank": 4, "single_comments": 1}, "yogeshojha.rengine/tools/OneForAll/modules/altdns.py": {"loc": 212, "lloc": 140, "sloc": 132, "comments": 24, "multi": 29, "blank": 29, "single_comments": 22}, "yogeshojha.rengine/tools/OneForAll/modules/collect.py": {"loc": 69, "lloc": 45, "sloc": 44, "comments": 6, "multi": 9, "blank": 10, "single_comments": 6}, "yogeshojha.rengine/tools/OneForAll/modules/enrich.py": {"loc": 72, "lloc": 62, "sloc": 63, "comments": 0, "multi": 0, "blank": 9, "single_comments": 0}, "yogeshojha.rengine/tools/OneForAll/modules/finder.py": {"loc": 205, "lloc": 157, "sloc": 178, "comments": 6, "multi": 0, "blank": 26, "single_comments": 1}, "yogeshojha.rengine/tools/OneForAll/modules/iscdn.py": {"loc": 86, "lloc": 70, "sloc": 69, "comments": 2, "multi": 0, "blank": 15, "single_comments": 2}, "yogeshojha.rengine/tools/OneForAll/modules/srv.py": {"loc": 75, "lloc": 60, "sloc": 59, "comments": 0, "multi": 3, "blank": 13, "single_comments": 0}, "yogeshojha.rengine/tools/OneForAll/modules/wildcard.py": {"loc": 322, "lloc": 228, "sloc": 228, "comments": 14, "multi": 45, "blank": 43, "single_comments": 6}, "yogeshojha.rengine/tools/OneForAll/modules/autotake/github.py": {"loc": 105, "lloc": 56, "sloc": 90, "comments": 13, "multi": 3, "blank": 5, "single_comments": 7}, "yogeshojha.rengine/tools/OneForAll/modules/certificates/censys_api.py": {"loc": 69, "lloc": 50, "sloc": 50, "comments": 1, "multi": 10, "blank": 9, "single_comments": 0}, "yogeshojha.rengine/tools/OneForAll/modules/certificates/certspotter.py": {"loc": 48, "lloc": 30, "sloc": 28, "comments": 0, "multi": 10, "blank": 10, "single_comments": 0}, "yogeshojha.rengine/tools/OneForAll/modules/certificates/crtsh.py": {"loc": 49, "lloc": 34, "sloc": 30, "comments": 0, "multi": 10, "blank": 9, "single_comments": 0}, "yogeshojha.rengine/tools/OneForAll/modules/certificates/google.py": {"loc": 48, "lloc": 30, "sloc": 29, "comments": 0, "multi": 10, "blank": 9, "single_comments": 0}, "yogeshojha.rengine/tools/OneForAll/modules/check/axfr.py": {"loc": 97, "lloc": 62, "sloc": 61, "comments": 1, "multi": 22, "blank": 13, "single_comments": 1}, "yogeshojha.rengine/tools/OneForAll/modules/check/cdx.py": {"loc": 44, "lloc": 26, "sloc": 22, "comments": 0, "multi": 13, "blank": 9, "single_comments": 0}, "yogeshojha.rengine/tools/OneForAll/modules/check/cert.py": {"loc": 58, "lloc": 39, "sloc": 35, "comments": 0, "multi": 13, "blank": 10, "single_comments": 0}, "yogeshojha.rengine/tools/OneForAll/modules/check/csp.py": {"loc": 94, "lloc": 62, "sloc": 59, "comments": 0, "multi": 21, "blank": 14, "single_comments": 0}, "yogeshojha.rengine/tools/OneForAll/modules/check/nsec.py": {"loc": 55, "lloc": 38, "sloc": 36, "comments": 4, "multi": 7, "blank": 10, "single_comments": 2}, "yogeshojha.rengine/tools/OneForAll/modules/check/robots.py": {"loc": 44, "lloc": 26, "sloc": 22, "comments": 0, "multi": 13, "blank": 9, "single_comments": 0}, "yogeshojha.rengine/tools/OneForAll/modules/check/sitemap.py": {"loc": 44, "lloc": 26, "sloc": 22, "comments": 0, "multi": 13, "blank": 9, "single_comments": 0}, "yogeshojha.rengine/tools/OneForAll/modules/crawl/archivecrawl.py": {"loc": 59, "lloc": 39, "sloc": 36, "comments": 1, "multi": 11, "blank": 11, "single_comments": 1}, "yogeshojha.rengine/tools/OneForAll/modules/crawl/commoncrawl.py": {"loc": 59, "lloc": 38, "sloc": 35, "comments": 1, "multi": 11, "blank": 12, "single_comments": 1}, "yogeshojha.rengine/tools/OneForAll/modules/datasets/anubis.py": {"loc": 45, "lloc": 29, "sloc": 26, "comments": 0, "multi": 10, "blank": 9, "single_comments": 0}, "yogeshojha.rengine/tools/OneForAll/modules/datasets/binaryedge_api.py": {"loc": 50, "lloc": 35, "sloc": 31, "comments": 0, "multi": 10, "blank": 9, "single_comments": 0}, "yogeshojha.rengine/tools/OneForAll/modules/datasets/cebaidu.py": {"loc": 45, "lloc": 30, "sloc": 26, "comments": 0, "multi": 10, "blank": 9, "single_comments": 0}, "yogeshojha.rengine/tools/OneForAll/modules/datasets/chinaz.py": {"loc": 45, "lloc": 29, "sloc": 26, "comments": 0, "multi": 10, "blank": 9, "single_comments": 0}, "yogeshojha.rengine/tools/OneForAll/modules/datasets/chinaz_api.py": {"loc": 49, "lloc": 34, "sloc": 30, "comments": 0, "multi": 10, "blank": 9, "single_comments": 0}, "yogeshojha.rengine/tools/OneForAll/modules/datasets/circl_api.py": {"loc": 49, "lloc": 33, "sloc": 30, "comments": 0, "multi": 10, "blank": 9, "single_comments": 0}, "yogeshojha.rengine/tools/OneForAll/modules/datasets/cloudflare_api.py": {"loc": 130, "lloc": 105, "sloc": 106, "comments": 2, "multi": 10, "blank": 12, "single_comments": 2}, "yogeshojha.rengine/tools/OneForAll/modules/datasets/dnsdb_api.py": {"loc": 51, "lloc": 35, "sloc": 31, "comments": 0, "multi": 10, "blank": 10, "single_comments": 0}, "yogeshojha.rengine/tools/OneForAll/modules/datasets/dnsdumpster.py": {"loc": 51, "lloc": 36, "sloc": 32, "comments": 0, "multi": 10, "blank": 9, "single_comments": 0}, "yogeshojha.rengine/tools/OneForAll/modules/datasets/hackertarget.py": {"loc": 45, "lloc": 30, "sloc": 26, "comments": 0, "multi": 10, "blank": 9, "single_comments": 0}, "yogeshojha.rengine/tools/OneForAll/modules/datasets/ip138.py": {"loc": 45, "lloc": 29, "sloc": 26, "comments": 0, "multi": 10, "blank": 9, "single_comments": 0}, "yogeshojha.rengine/tools/OneForAll/modules/datasets/ipv4info_api.py": {"loc": 73, "lloc": 55, "sloc": 52, "comments": 4, "multi": 10, "blank": 9, "single_comments": 2}, "yogeshojha.rengine/tools/OneForAll/modules/datasets/netcraft.py": {"loc": 84, "lloc": 63, "sloc": 60, "comments": 3, "multi": 13, "blank": 11, "single_comments": 0}, "yogeshojha.rengine/tools/OneForAll/modules/datasets/passivedns_api.py": {"loc": 51, "lloc": 36, "sloc": 32, "comments": 0, "multi": 10, "blank": 9, "single_comments": 0}, "yogeshojha.rengine/tools/OneForAll/modules/datasets/qianxun.py": {"loc": 61, "lloc": 40, "sloc": 41, "comments": 1, "multi": 10, "blank": 10, "single_comments": 0}, "yogeshojha.rengine/tools/OneForAll/modules/datasets/rapiddns.py": {"loc": 45, "lloc": 30, "sloc": 26, "comments": 0, "multi": 10, "blank": 9, "single_comments": 0}, "yogeshojha.rengine/tools/OneForAll/modules/datasets/riddler.py": {"loc": 45, "lloc": 30, "sloc": 26, "comments": 0, "multi": 10, "blank": 9, "single_comments": 0}, "yogeshojha.rengine/tools/OneForAll/modules/datasets/robtex.py": {"loc": 58, "lloc": 41, "sloc": 38, "comments": 1, "multi": 10, "blank": 10, "single_comments": 0}, "yogeshojha.rengine/tools/OneForAll/modules/datasets/securitytrails_api.py": {"loc": 56, "lloc": 41, "sloc": 37, "comments": 1, "multi": 10, "blank": 9, "single_comments": 0}, "yogeshojha.rengine/tools/OneForAll/modules/datasets/sitedossier.py": {"loc": 57, "lloc": 39, "sloc": 36, "comments": 2, "multi": 10, "blank": 10, "single_comments": 1}, "yogeshojha.rengine/tools/OneForAll/modules/datasets/spyse_api.py": {"loc": 62, "lloc": 48, "sloc": 43, "comments": 1, "multi": 10, "blank": 9, "single_comments": 0}, "yogeshojha.rengine/tools/OneForAll/modules/datasets/sublist3r.py": {"loc": 45, "lloc": 30, "sloc": 26, "comments": 0, "multi": 10, "blank": 9, "single_comments": 0}, "yogeshojha.rengine/tools/OneForAll/modules/datasets/wzpc.py": {"loc": 68, "lloc": 50, "sloc": 48, "comments": 1, "multi": 10, "blank": 10, "single_comments": 0}, "yogeshojha.rengine/tools/OneForAll/modules/dnsquery/mx.py": {"loc": 35, "lloc": 22, "sloc": 20, "comments": 1, "multi": 7, "blank": 8, "single_comments": 0}, "yogeshojha.rengine/tools/OneForAll/modules/dnsquery/ns.py": {"loc": 35, "lloc": 22, "sloc": 20, "comments": 1, "multi": 7, "blank": 8, "single_comments": 0}, "yogeshojha.rengine/tools/OneForAll/modules/dnsquery/soa.py": {"loc": 35, "lloc": 22, "sloc": 20, "comments": 1, "multi": 7, "blank": 8, "single_comments": 0}, "yogeshojha.rengine/tools/OneForAll/modules/dnsquery/spf.py": {"loc": 35, "lloc": 22, "sloc": 20, "comments": 1, "multi": 7, "blank": 8, "single_comments": 0}, "yogeshojha.rengine/tools/OneForAll/modules/dnsquery/txt.py": {"loc": 35, "lloc": 22, "sloc": 20, "comments": 1, "multi": 7, "blank": 8, "single_comments": 0}, "yogeshojha.rengine/tools/OneForAll/modules/intelligence/alienvault.py": {"loc": 50, "lloc": 32, "sloc": 29, "comments": 0, "multi": 10, "blank": 11, "single_comments": 0}, "yogeshojha.rengine/tools/OneForAll/modules/intelligence/riskiq_api.py": {"loc": 57, "lloc": 41, "sloc": 38, "comments": 0, "multi": 10, "blank": 9, "single_comments": 0}, "yogeshojha.rengine/tools/OneForAll/modules/intelligence/threatbook_api.py": {"loc": 50, "lloc": 34, "sloc": 31, "comments": 0, "multi": 10, "blank": 9, "single_comments": 0}, "yogeshojha.rengine/tools/OneForAll/modules/intelligence/threatminer.py": {"loc": 46, "lloc": 30, "sloc": 27, "comments": 0, "multi": 10, "blank": 9, "single_comments": 0}, "yogeshojha.rengine/tools/OneForAll/modules/intelligence/virustotal.py": {"loc": 60, "lloc": 42, "sloc": 37, "comments": 0, "multi": 13, "blank": 10, "single_comments": 0}, "yogeshojha.rengine/tools/OneForAll/modules/intelligence/virustotal_api.py": {"loc": 57, "lloc": 43, "sloc": 38, "comments": 0, "multi": 10, "blank": 9, "single_comments": 0}, "yogeshojha.rengine/tools/OneForAll/modules/search/ask.py": {"loc": 69, "lloc": 48, "sloc": 44, "comments": 4, "multi": 12, "blank": 11, "single_comments": 2}, "yogeshojha.rengine/tools/OneForAll/modules/search/baidu.py": {"loc": 96, "lloc": 64, "sloc": 61, "comments": 9, "multi": 17, "blank": 13, "single_comments": 5}, "yogeshojha.rengine/tools/OneForAll/modules/search/bing.py": {"loc": 79, "lloc": 55, "sloc": 52, "comments": 7, "multi": 12, "blank": 12, "single_comments": 3}, "yogeshojha.rengine/tools/OneForAll/modules/search/bing_api.py": {"loc": 78, "lloc": 55, "sloc": 52, "comments": 6, "multi": 12, "blank": 12, "single_comments": 2}, "yogeshojha.rengine/tools/OneForAll/modules/search/fofa_api.py": {"loc": 74, "lloc": 53, "sloc": 54, "comments": 1, "multi": 10, "blank": 10, "single_comments": 0}, "yogeshojha.rengine/tools/OneForAll/modules/search/gitee.py": {"loc": 70, "lloc": 55, "sloc": 51, "comments": 0, "multi": 10, "blank": 9, "single_comments": 0}, "yogeshojha.rengine/tools/OneForAll/modules/search/github_api.py": {"loc": 109, "lloc": 87, "sloc": 82, "comments": 0, "multi": 14, "blank": 13, "single_comments": 0}, "yogeshojha.rengine/tools/OneForAll/modules/search/google.py": {"loc": 83, "lloc": 59, "sloc": 56, "comments": 2, "multi": 12, "blank": 13, "single_comments": 2}, "yogeshojha.rengine/tools/OneForAll/modules/search/google_api.py": {"loc": 77, "lloc": 53, "sloc": 51, "comments": 4, "multi": 12, "blank": 12, "single_comments": 2}, "yogeshojha.rengine/tools/OneForAll/modules/search/shodan_api.py": {"loc": 53, "lloc": 38, "sloc": 34, "comments": 0, "multi": 10, "blank": 9, "single_comments": 0}, "yogeshojha.rengine/tools/OneForAll/modules/search/so.py": {"loc": 75, "lloc": 50, "sloc": 46, "comments": 6, "multi": 12, "blank": 13, "single_comments": 4}, "yogeshojha.rengine/tools/OneForAll/modules/search/sogou.py": {"loc": 72, "lloc": 47, "sloc": 44, "comments": 5, "multi": 12, "blank": 12, "single_comments": 4}, "yogeshojha.rengine/tools/OneForAll/modules/search/yahoo.py": {"loc": 80, "lloc": 58, "sloc": 54, "comments": 7, "multi": 12, "blank": 12, "single_comments": 2}, "yogeshojha.rengine/tools/OneForAll/modules/search/yandex.py": {"loc": 79, "lloc": 55, "sloc": 52, "comments": 7, "multi": 12, "blank": 13, "single_comments": 2}, "yogeshojha.rengine/tools/OneForAll/modules/search/zoomeye_api.py": {"loc": 86, "lloc": 70, "sloc": 63, "comments": 1, "multi": 13, "blank": 10, "single_comments": 0}, "yogeshojha.rengine/tools/Sublist3r/setup.py": {"loc": 36, "lloc": 3, "sloc": 35, "comments": 0, "multi": 0, "blank": 1, "single_comments": 0}, "yogeshojha.rengine/tools/Sublist3r/sublist3r.py": {"loc": 1013, "lloc": 797, "sloc": 806, "comments": 41, "multi": 19, "blank": 154, "single_comments": 34}, "yogeshojha.rengine/tools/Sublist3r/subbrute/subbrute.py": {"loc": 635, "lloc": 447, "sloc": 452, "comments": 146, "multi": 0, "blank": 42, "single_comments": 141}, "yogeshojha.rengine/tools/Sublist3r/subbrute/__init__.py": {"loc": 0, "lloc": 0, "sloc": 0, "comments": 0, "multi": 0, "blank": 0, "single_comments": 0}}
